{"bloque":"precip_cua","bloques":[{"clave":"precip_det","etiqueta":"Precipitaci\u00f3n: detecci\u00f3n"},{"clave":"precip_cua","etiqueta":"Precipitaci\u00f3n: cuantificaci\u00f3n"},{"clave":"tmax","etiqueta":"Temperatura m\u00e1xima"},{"clave":"tmin","etiqueta":"Temperatura m\u00ednima"}],"estaciones":[{"codigo":"M5190","nombre":"Captaci\u00f3n Central","region":"Amazonia"},{"codigo":"M5187","nombre":"El Chaco 1","region":"Amazonia"},{"codigo":"M5189","nombre":"El Chaco 2","region":"Amazonia"},{"codigo":"84099","nombre":"El Coca","region":"Amazonia"},{"codigo":"84253","nombre":"Gualaquiza","region":"Amazonia"},{"codigo":"CP03","nombre":"Guarumales","region":"Amazonia"},{"codigo":"84151","nombre":"Jumandy","region":"Amazonia"},{"codigo":"84063","nombre":"Lago Agrio","region":"Amazonia"},{"codigo":"84217","nombre":"Macas","region":"Amazonia"},{"codigo":"M1040","nombre":"Macas INA","region":"Amazonia"},{"codigo":"84132","nombre":"N. Rocafu","region":"Amazonia"},{"codigo":"M0188","nombre":"Papallacta","region":"Amazonia"},{"codigo":"84163","nombre":"Pastaza","region":"Amazonia"},{"codigo":"84179","nombre":"Puyo","region":"Amazonia"},{"codigo":"M5008","nombre":"Quijos-Cosan","region":"Amazonia"},{"codigo":"M5254","nombre":"Salve Faccha","region":"Amazonia"},{"codigo":"M1124","nombre":"Sierra Azul","region":"Amazonia"},{"codigo":"M1219","nombre":"Tena Hda","region":"Amazonia"},{"codigo":"M5021","nombre":"Yura Faccha Oyacachi","region":"Amazonia"},{"codigo":"84001","nombre":"Baltra","region":"Insular"},{"codigo":"84008","nombre":"S. Cristobal","region":"Insular"},{"codigo":"84010","nombre":"S. Cristobal A","region":"Insular"},{"codigo":"84147","nombre":"Ambato","region":"Interandina"},{"codigo":"CP01","nombre":"Arenales","region":"Interandina"},{"codigo":"M0055","nombre":"Bicenten","region":"Interandina"},{"codigo":"M5101","nombre":"Calder\u00f3n","region":"Interandina"},{"codigo":"84226","nombre":"Ca\u00f1ar","region":"Interandina"},{"codigo":"CP02","nombre":"Celec Cuenca","region":"Interandina"},{"codigo":"84239","nombre":"Cuenca","region":"Interandina"},{"codigo":"84173","nombre":"ESPOCH","region":"Interandina"},{"codigo":"M0102","nombre":"El \u00c1ngel","region":"Interandina"},{"codigo":"M1240","nombre":"Ibarra","region":"Interandina"},{"codigo":"84045","nombre":"Inguincho","region":"Interandina"},{"codigo":"84088","nombre":"Izobamba","region":"Interandina"},{"codigo":"M0024","nombre":"I\u00f1aquito","region":"Interandina"},{"codigo":"M0124","nombre":"La Man\u00e1","region":"Interandina"},{"codigo":"84076","nombre":"La Tola","region":"Interandina"},{"codigo":"84265","nombre":"La Toma","region":"Interandina"},{"codigo":"84123","nombre":"Latacunga","region":"Interandina"},{"codigo":"84270","nombre":"Loja Argelia","region":"Interandina"},{"codigo":"M0105","nombre":"Otavalo","region":"Interandina"},{"codigo":"M0391","nombre":"Pallatanga","region":"Interandina"},{"codigo":"84160","nombre":"Querochaca","region":"Interandina"},{"codigo":"84176","nombre":"Riobamba","region":"Interandina"},{"codigo":"84143","nombre":"Rumipamba","region":"Interandina"},{"codigo":"84036","nombre":"S. Gabriel","region":"Interandina"},{"codigo":"M1274","nombre":"Salesiana","region":"Interandina"},{"codigo":"CP04","nombre":"Sevilla","region":"Interandina"},{"codigo":"CP05","nombre":"Sta.B\u00e1rbara","region":"Interandina"},{"codigo":"84075","nombre":"Tababela","region":"Interandina"},{"codigo":"84056","nombre":"Tomal\u00f3n","region":"Interandina"},{"codigo":"84027","nombre":"Tulc\u00e1n","region":"Interandina"},{"codigo":"M0162","nombre":"Chone","region":"Litoral"},{"codigo":"HM002","nombre":"Daule","region":"Litoral"},{"codigo":"84018","nombre":"Esmeraldas","region":"Litoral"},{"codigo":"84203","nombre":"Guayaquil","region":"Litoral"},{"codigo":"M1271","nombre":"Gye(Facult)","region":"Litoral"},{"codigo":"M5135","nombre":"Huaquillas","region":"Litoral"},{"codigo":"84050","nombre":"La Concordia","region":"Litoral"},{"codigo":"M1170","nombre":"La Libertad","region":"Litoral"},{"codigo":"M5090","nombre":"La Troncal","region":"Litoral"},{"codigo":"84117","nombre":"Manta","region":"Litoral"},{"codigo":"M0037","nombre":"Milagro","region":"Litoral"},{"codigo":"M1207","nombre":"Nobol","region":"Litoral"},{"codigo":"M1253","nombre":"P. Hondo","region":"Litoral"},{"codigo":"84140","nombre":"Pichilingue","region":"Litoral"},{"codigo":"84135","nombre":"Portoviejo","region":"Litoral"},{"codigo":"84105","nombre":"Puerto Ila","region":"Litoral"},{"codigo":"M0156","nombre":"Quinind\u00e9","region":"Litoral"},{"codigo":"84200","nombre":"Salinas","region":"Litoral"},{"codigo":"84252","nombre":"Sta. Rosa","region":"Litoral"}],"familia":"Convencionales","ganadores":[{"bias":-0.02,"codigo":"84200","color":"#004E89","confianza":"Alta","corr":0.83,"familia":"Convencionales","lat":-2.2,"lon":-80.98972,"mae":1.0,"modelo":"IFSHRES","n":266,"nombre":"Salinas","rating":8.45,"region":"Litoral","rmse":3.83},{"bias":0.77,"codigo":"M5135","color":"#E69F00","confianza":"Alta","corr":0.25,"familia":"Convencionales","lat":-3.48205,"lon":-80.2275,"mae":0.94,"modelo":"GFS05","n":137,"nombre":"Huaquillas","rating":8.1,"region":"Litoral","rmse":1.98},{"bias":-0.45,"codigo":"M1170","color":"#56B4E9","confianza":"Alta","corr":0.6,"familia":"Convencionales","lat":-2.23358,"lon":-80.87507,"mae":1.07,"modelo":"AIFS025","n":114,"nombre":"La Libertad","rating":7.91,"region":"Litoral","rmse":4.98},{"bias":-0.91,"codigo":"84147","color":"#009E73","confianza":"Alta","corr":0.59,"familia":"Convencionales","lat":-1.21413,"lon":-78.57455,"mae":1.25,"modelo":"ICON","n":111,"nombre":"Ambato","rating":7.9,"region":"Interandina","rmse":3.69},{"bias":-0.41,"codigo":"84252","color":"#56B4E9","confianza":"Alta","corr":0.77,"familia":"Convencionales","lat":-3.43583,"lon":-79.98333,"mae":1.73,"modelo":"AIFS025","n":112,"nombre":"Sta. Rosa","rating":7.88,"region":"Litoral","rmse":4.04},{"bias":0.18,"codigo":"M0037","color":"#009E73","confianza":"Alta","corr":0.81,"familia":"Convencionales","lat":-2.11805,"lon":-79.60038,"mae":1.53,"modelo":"ICON","n":38,"nombre":"Milagro","rating":7.86,"region":"Litoral","rmse":5.45},{"bias":0.6,"codigo":"M5090","color":"#0072B2","confianza":"Alta","corr":0.42,"familia":"Convencionales","lat":-2.52865,"lon":-79.50257,"mae":1.39,"modelo":"IFS025","n":80,"nombre":"La Troncal","rating":7.68,"region":"Litoral","rmse":4.09},{"bias":-0.78,"codigo":"84176","color":"#009E73","confianza":"Alta","corr":0.33,"familia":"Convencionales","lat":-1.65333,"lon":-78.54889,"mae":1.5,"modelo":"ICON","n":185,"nombre":"Riobamba","rating":7.53,"region":"Interandina","rmse":3.88},{"bias":-0.31,"codigo":"84265","color":"#009E73","confianza":"Alta","corr":0.38,"familia":"Convencionales","lat":-3.99556,"lon":-79.37167,"mae":1.69,"modelo":"ICON","n":277,"nombre":"La Toma","rating":7.52,"region":"Interandina","rmse":4.37},{"bias":-0.46,"codigo":"84117","color":"#009E73","confianza":"Alta","corr":0.24,"familia":"Convencionales","lat":-0.95,"lon":-80.68333,"mae":1.21,"modelo":"ICON","n":281,"nombre":"Manta","rating":7.51,"region":"Litoral","rmse":4.99},{"bias":1.11,"codigo":"CP04","color":"#56B4E9","confianza":"Alta","corr":0.44,"familia":"Convencionales","lat":-2.79976,"lon":-78.65003,"mae":2.35,"modelo":"AIFS025","n":58,"nombre":"Sevilla","rating":7.29,"region":"Interandina","rmse":3.14},{"bias":-0.52,"codigo":"84123","color":"#009E73","confianza":"Alta","corr":0.24,"familia":"Convencionales","lat":-0.91333,"lon":-78.61556,"mae":1.99,"modelo":"ICON","n":279,"nombre":"Latacunga","rating":7.22,"region":"Interandina","rmse":4.29},{"bias":-1.24,"codigo":"84173","color":"#009E73","confianza":"Alta","corr":0.28,"familia":"Convencionales","lat":-1.65083,"lon":-78.68521,"mae":1.75,"modelo":"ICON","n":277,"nombre":"ESPOCH","rating":7.2,"region":"Interandina","rmse":4.33},{"bias":1.84,"codigo":"M1207","color":"#56B4E9","confianza":"Alta","corr":0.68,"familia":"Convencionales","lat":-1.92154,"lon":-80.06279,"mae":2.42,"modelo":"AIFS025","n":65,"nombre":"Nobol","rating":7.17,"region":"Litoral","rmse":4.06},{"bias":-0.76,"codigo":"84001","color":"#009E73","confianza":"Alta","corr":0.38,"familia":"Convencionales","lat":-0.445,"lon":-90.269,"mae":1.51,"modelo":"ICON","n":276,"nombre":"Baltra","rating":7.11,"region":"Insular","rmse":7.27},{"bias":-1.4,"codigo":"84160","color":"#009E73","confianza":"Alta","corr":0.24,"familia":"Convencionales","lat":-1.3671,"lon":-78.60554,"mae":1.94,"modelo":"ICON","n":276,"nombre":"Querochaca","rating":7.02,"region":"Interandina","rmse":4.4},{"bias":0.44,"codigo":"M0024","color":"#56B4E9","confianza":"Alta","corr":0.63,"familia":"Convencionales","lat":-0.1783,"lon":-78.48773,"mae":3.11,"modelo":"AIFS025","n":113,"nombre":"I\u00f1aquito","rating":6.99,"region":"Interandina","rmse":5.19},{"bias":-1.32,"codigo":"84143","color":"#009E73","confianza":"Alta","corr":0.32,"familia":"Convencionales","lat":-1.01998,"lon":-78.59456,"mae":2.1,"modelo":"ICON","n":275,"nombre":"Rumipamba","rating":6.94,"region":"Interandina","rmse":5.05},{"bias":-1.39,"codigo":"CP05","color":"#009E73","confianza":"Alta","corr":0.15,"familia":"Convencionales","lat":-2.86493,"lon":-78.77274,"mae":1.99,"modelo":"ICON","n":122,"nombre":"Sta.B\u00e1rbara","rating":6.91,"region":"Interandina","rmse":4.45},{"bias":0.83,"codigo":"M0102","color":"#56B4E9","confianza":"Alta","corr":0.42,"familia":"Convencionales","lat":0.619,"lon":-77.94496,"mae":2.69,"modelo":"AIFS025","n":114,"nombre":"El \u00c1ngel","rating":6.91,"region":"Interandina","rmse":4.89},{"bias":-0.74,"codigo":"84075","color":"#009E73","confianza":"Alta","corr":0.16,"familia":"Convencionales","lat":-0.14083,"lon":-78.353,"mae":2.2,"modelo":"ICON","n":278,"nombre":"Tababela","rating":6.9,"region":"Interandina","rmse":4.94},{"bias":0.35,"codigo":"M0188","color":"#004E89","confianza":"Alta","corr":0.37,"familia":"Convencionales","lat":-0.38062,"lon":-78.1414,"mae":3.16,"modelo":"IFSHRES","n":253,"nombre":"Papallacta","rating":6.83,"region":"Amazonia","rmse":4.69},{"bias":-0.4,"codigo":"84270","color":"#009E73","confianza":"Alta","corr":0.24,"familia":"Convencionales","lat":-4.0375,"lon":-79.2034,"mae":2.64,"modelo":"ICON","n":274,"nombre":"Loja Argelia","rating":6.79,"region":"Interandina","rmse":5.46},{"bias":-1.14,"codigo":"CP02","color":"#009E73","confianza":"Alta","corr":0.28,"familia":"Convencionales","lat":-2.85926,"lon":-78.93337,"mae":2.42,"modelo":"ICON","n":136,"nombre":"Celec Cuenca","rating":6.78,"region":"Interandina","rmse":5.23},{"bias":0.95,"codigo":"84226","color":"#0072B2","confianza":"Alta","corr":0.27,"familia":"Convencionales","lat":-2.55221,"lon":-78.94519,"mae":2.94,"modelo":"IFS025","n":274,"nombre":"Ca\u00f1ar","rating":6.72,"region":"Interandina","rmse":4.43},{"bias":1.01,"codigo":"M1274","color":"#56B4E9","confianza":"Alta","corr":0.45,"familia":"Convencionales","lat":-0.28192,"lon":-78.55024,"mae":3.23,"modelo":"AIFS025","n":107,"nombre":"Salesiana","rating":6.69,"region":"Interandina","rmse":4.91},{"bias":-1.41,"codigo":"M5254","color":"#56B4E9","confianza":"Alta","corr":0.43,"familia":"Convencionales","lat":-0.23383,"lon":-78.16968,"mae":2.99,"modelo":"AIFS025","n":101,"nombre":"Salve Faccha","rating":6.68,"region":"Amazonia","rmse":4.92},{"bias":-1.57,"codigo":"M1240","color":"#009E73","confianza":"Alta","corr":0.18,"familia":"Convencionales","lat":0.32978,"lon":-78.1322,"mae":2.28,"modelo":"ICON","n":276,"nombre":"Ibarra","rating":6.66,"region":"Interandina","rmse":5.2},{"bias":-1.31,"codigo":"84027","color":"#009E73","confianza":"Alta","corr":0.21,"familia":"Convencionales","lat":0.81667,"lon":-77.7,"mae":2.36,"modelo":"ICON","n":181,"nombre":"Tulc\u00e1n","rating":6.62,"region":"Interandina","rmse":5.8},{"bias":0.7,"codigo":"M0055","color":"#56B4E9","confianza":"Alta","corr":0.48,"familia":"Convencionales","lat":-0.14111,"lon":-78.48714,"mae":3.46,"modelo":"AIFS025","n":114,"nombre":"Bicenten","rating":6.59,"region":"Interandina","rmse":5.72},{"bias":0.65,"codigo":"84056","color":"#009E73","confianza":"Alta","corr":0.24,"familia":"Convencionales","lat":0.01116,"lon":-78.25505,"mae":2.92,"modelo":"ICON","n":270,"nombre":"Tomal\u00f3n","rating":6.58,"region":"Interandina","rmse":5.72},{"bias":-0.08,"codigo":"M0105","color":"#009E73","confianza":"Alta","corr":0.29,"familia":"Convencionales","lat":0.24342,"lon":-78.25006,"mae":3.3,"modelo":"ICON","n":280,"nombre":"Otavalo","rating":6.56,"region":"Interandina","rmse":6.18},{"bias":-0.45,"codigo":"84036","color":"#004E89","confianza":"Alta","corr":0.44,"familia":"Convencionales","lat":0.60417,"lon":-77.81944,"mae":3.44,"modelo":"IFSHRES","n":266,"nombre":"S. Gabriel","rating":6.55,"region":"Interandina","rmse":6.28},{"bias":2.95,"codigo":"HM002","color":"#56B4E9","confianza":"Alta","corr":0.61,"familia":"Convencionales","lat":-1.85449,"lon":-79.98518,"mae":3.11,"modelo":"AIFS025","n":111,"nombre":"Daule","rating":6.54,"region":"Litoral","rmse":4.78},{"bias":-1.19,"codigo":"84135","color":"#009E73","confianza":"Alta","corr":0.52,"familia":"Convencionales","lat":-1.17343,"lon":-80.38736,"mae":2.7,"modelo":"ICON","n":277,"nombre":"Portoviejo","rating":6.52,"region":"Litoral","rmse":7.96},{"bias":-0.8,"codigo":"84045","color":"#56B4E9","confianza":"Alta","corr":0.44,"familia":"Convencionales","lat":0.25694,"lon":-78.40524,"mae":3.09,"modelo":"AIFS025","n":111,"nombre":"Inguincho","rating":6.52,"region":"Interandina","rmse":6.87},{"bias":-1.87,"codigo":"84010","color":"#E69F00","confianza":"Alta","corr":0.48,"familia":"Convencionales","lat":-0.909,"lon":-89.617,"mae":2.58,"modelo":"GFS05","n":269,"nombre":"S. Cristobal A","rating":6.42,"region":"Insular","rmse":7.72},{"bias":0.83,"codigo":"M5101","color":"#56B4E9","confianza":"Alta","corr":0.41,"familia":"Convencionales","lat":-0.07737,"lon":-78.43295,"mae":3.56,"modelo":"AIFS025","n":101,"nombre":"Calder\u00f3n","rating":6.41,"region":"Interandina","rmse":6.12},{"bias":-0.99,"codigo":"M5021","color":"#004E89","confianza":"Alta","corr":0.35,"familia":"Convencionales","lat":-0.18836,"lon":-78.11066,"mae":3.61,"modelo":"IFSHRES","n":134,"nombre":"Yura Faccha Oyacachi","rating":6.37,"region":"Amazonia","rmse":5.64},{"bias":-2.24,"codigo":"84008","color":"#E69F00","confianza":"Alta","corr":0.48,"familia":"Convencionales","lat":-0.90406,"lon":-89.61431,"mae":2.77,"modelo":"GFS05","n":241,"nombre":"S. Cristobal","rating":6.35,"region":"Insular","rmse":7.13},{"bias":-0.44,"codigo":"M0162","color":"#E69F00","confianza":"Alta","corr":0.43,"familia":"Convencionales","lat":-0.6308,"lon":-80.03651,"mae":3.64,"modelo":"GFS05","n":280,"nombre":"Chone","rating":6.31,"region":"Litoral","rmse":7.57},{"bias":-0.1,"codigo":"84239","color":"#E69F00","confianza":"Alta","corr":0.21,"familia":"Convencionales","lat":-2.88917,"lon":-78.98417,"mae":3.74,"modelo":"GFS05","n":279,"nombre":"Cuenca","rating":6.3,"region":"Interandina","rmse":6.52},{"bias":-0.57,"codigo":"M1253","color":"#56B4E9","confianza":"Alta","corr":0.58,"familia":"Convencionales","lat":-2.1925,"lon":-80.02417,"mae":3.41,"modelo":"AIFS025","n":110,"nombre":"P. Hondo","rating":6.3,"region":"Litoral","rmse":9.44},{"bias":-1.92,"codigo":"84076","color":"#009E73","confianza":"Alta","corr":0.33,"familia":"Convencionales","lat":-0.23179,"lon":-78.37043,"mae":3.04,"modelo":"ICON","n":278,"nombre":"La Tola","rating":6.21,"region":"Interandina","rmse":6.8},{"bias":-0.51,"codigo":"84018","color":"#009E73","confianza":"Alta","corr":0.17,"familia":"Convencionales","lat":0.97917,"lon":-79.62444,"mae":2.8,"modelo":"ICON","n":256,"nombre":"Esmeraldas","rating":6.1,"region":"Litoral","rmse":10.28},{"bias":0.54,"codigo":"M1271","color":"#0072B2","confianza":"Alta","corr":0.49,"familia":"Convencionales","lat":-2.14646,"lon":-79.91734,"mae":4.07,"modelo":"IFS025","n":274,"nombre":"Gye(Facult)","rating":5.89,"region":"Litoral","rmse":10.84},{"bias":-0.59,"codigo":"84253","color":"#009E73","confianza":"Alta","corr":0.2,"familia":"Convencionales","lat":-3.42333,"lon":-78.56694,"mae":4.45,"modelo":"ICON","n":181,"nombre":"Gualaquiza","rating":5.75,"region":"Amazonia","rmse":8.27},{"bias":-0.39,"codigo":"84203","color":"#0072B2","confianza":"Alta","corr":0.55,"familia":"Convencionales","lat":-2.15333,"lon":-79.88333,"mae":4.64,"modelo":"IFS025","n":279,"nombre":"Guayaquil","rating":5.73,"region":"Litoral","rmse":12.05},{"bias":-1.23,"codigo":"84088","color":"#56B4E9","confianza":"Alta","corr":0.23,"familia":"Convencionales","lat":-0.36593,"lon":-78.55513,"mae":4.67,"modelo":"AIFS025","n":113,"nombre":"Izobamba","rating":5.54,"region":"Interandina","rmse":8.55},{"bias":0.34,"codigo":"M5190","color":"#56B4E9","confianza":"Alta","corr":0.34,"familia":"Convencionales","lat":-0.19886,"lon":-77.68304,"mae":7.83,"modelo":"AIFS025","n":101,"nombre":"Captaci\u00f3n Central","rating":5.03,"region":"Amazonia","rmse":10.57},{"bias":0.06,"codigo":"84217","color":"#56B4E9","confianza":"Alta","corr":0.24,"familia":"Convencionales","lat":-2.29861,"lon":-78.12056,"mae":7.83,"modelo":"AIFS025","n":113,"nombre":"Macas","rating":4.93,"region":"Amazonia","rmse":11.57},{"bias":0.0,"codigo":"84132","color":"#0072B2","confianza":"Alta","corr":0.28,"familia":"Convencionales","lat":-0.92003,"lon":-75.40303,"mae":8.21,"modelo":"IFS025","n":208,"nombre":"N. Rocafu","rating":4.85,"region":"Amazonia","rmse":12.52},{"bias":0.12,"codigo":"84140","color":"#56B4E9","confianza":"Alta","corr":0.54,"familia":"Convencionales","lat":-1.07434,"lon":-79.4929,"mae":8.37,"modelo":"AIFS025","n":112,"nombre":"Pichilingue","rating":4.82,"region":"Litoral","rmse":16.35},{"bias":2.94,"codigo":"84151","color":"#56B4E9","confianza":"Alta","corr":0.33,"familia":"Convencionales","lat":-1.057,"lon":-77.584,"mae":7.28,"modelo":"AIFS025","n":57,"nombre":"Jumandy","rating":4.76,"region":"Amazonia","rmse":8.77},{"bias":-0.68,"codigo":"84050","color":"#0072B2","confianza":"Alta","corr":0.36,"familia":"Convencionales","lat":-0.02478,"lon":-79.38028,"mae":9.57,"modelo":"IFS025","n":268,"nombre":"La Concordia","rating":4.36,"region":"Litoral","rmse":16.83},{"bias":-2.56,"codigo":"M0391","color":"#E69F00","confianza":"Alta","corr":0.25,"familia":"Convencionales","lat":-2.00047,"lon":-78.97222,"mae":7.1,"modelo":"GFS05","n":130,"nombre":"Pallatanga","rating":4.29,"region":"Interandina","rmse":15.16},{"bias":-2.64,"codigo":"M0156","color":"#0072B2","confianza":"Alta","corr":0.38,"familia":"Convencionales","lat":0.31944,"lon":-79.47108,"mae":8.5,"modelo":"IFS025","n":280,"nombre":"Quinind\u00e9","rating":4.16,"region":"Litoral","rmse":15.95},{"bias":-1.96,"codigo":"M1040","color":"#0072B2","confianza":"Alta","corr":0.19,"familia":"Convencionales","lat":-2.22982,"lon":-78.12501,"mae":9.01,"modelo":"IFS025","n":264,"nombre":"Macas INA","rating":4.15,"region":"Amazonia","rmse":13.84},{"bias":-1.52,"codigo":"M0124","color":"#56B4E9","confianza":"Alta","corr":0.35,"familia":"Convencionales","lat":-0.90903,"lon":-79.25367,"mae":9.06,"modelo":"AIFS025","n":114,"nombre":"La Man\u00e1","rating":4.04,"region":"Interandina","rmse":21.88},{"bias":-0.29,"codigo":"84105","color":"#009E73","confianza":"Alta","corr":0.21,"familia":"Convencionales","lat":-0.493,"lon":-79.34892,"mae":11.38,"modelo":"ICON","n":280,"nombre":"Puerto Ila","rating":4.03,"region":"Litoral","rmse":20.31},{"bias":-3.35,"codigo":"M1124","color":"#56B4E9","confianza":"Alta","corr":0.28,"familia":"Convencionales","lat":-0.67418,"lon":-77.91936,"mae":9.81,"modelo":"AIFS025","n":75,"nombre":"Sierra Azul","rating":3.93,"region":"Amazonia","rmse":13.98},{"bias":-2.61,"codigo":"84099","color":"#004E89","confianza":"Alta","corr":0.39,"familia":"Convencionales","lat":-0.46056,"lon":-76.98806,"mae":10.02,"modelo":"IFSHRES","n":264,"nombre":"El Coca","rating":3.92,"region":"Amazonia","rmse":17.88},{"bias":-3.76,"codigo":"M5008","color":"#E69F00","confianza":"Alta","corr":0.15,"familia":"Convencionales","lat":-0.57833,"lon":-77.86833,"mae":9.22,"modelo":"GFS05","n":97,"nombre":"Quijos-Cosan","rating":3.77,"region":"Amazonia","rmse":14.68},{"bias":-4.99,"codigo":"CP01","color":"#0072B2","confianza":"Alta","corr":0.19,"familia":"Convencionales","lat":-2.56545,"lon":-78.56733,"mae":8.66,"modelo":"IFS025","n":135,"nombre":"Arenales","rating":3.75,"region":"Interandina","rmse":14.38},{"bias":-4.69,"codigo":"CP03","color":"#E69F00","confianza":"Alta","corr":0.07,"familia":"Convencionales","lat":-2.79945,"lon":-78.49954,"mae":8.18,"modelo":"GFS05","n":136,"nombre":"Guarumales","rating":3.75,"region":"Amazonia","rmse":14.14},{"bias":-6.19,"codigo":"M1219","color":"#E69F00","confianza":"Alta","corr":0.38,"familia":"Convencionales","lat":-0.91685,"lon":-77.81907,"mae":9.59,"modelo":"GFS05","n":46,"nombre":"Tena Hda","rating":3.74,"region":"Amazonia","rmse":13.94},{"bias":-2.24,"codigo":"84063","color":"#56B4E9","confianza":"Alta","corr":0.14,"familia":"Convencionales","lat":0.0925,"lon":-76.86944,"mae":10.97,"modelo":"AIFS025","n":113,"nombre":"Lago Agrio","rating":3.67,"region":"Amazonia","rmse":18.05},{"bias":-3.75,"codigo":"M5189","color":"#004E89","confianza":"Alta","corr":0.35,"familia":"Convencionales","lat":-0.13094,"lon":-77.45573,"mae":11.34,"modelo":"IFSHRES","n":79,"nombre":"El Chaco 2","rating":3.67,"region":"Amazonia","rmse":16.69},{"bias":-3.74,"codigo":"M5187","color":"#56B4E9","confianza":"Alta","corr":0.24,"familia":"Convencionales","lat":-0.13741,"lon":-77.47286,"mae":11.34,"modelo":"AIFS025","n":102,"nombre":"El Chaco 1","rating":3.59,"region":"Amazonia","rmse":16.27},{"bias":-4.3,"codigo":"84179","color":"#56B4E9","confianza":"Alta","corr":0.3,"familia":"Convencionales","lat":-1.5057,"lon":-77.956,"mae":10.65,"modelo":"AIFS025","n":112,"nombre":"Puyo","rating":3.57,"region":"Amazonia","rmse":17.37},{"bias":-7.19,"codigo":"84163","color":"#56B4E9","confianza":"Alta","corr":0.21,"familia":"Convencionales","lat":-1.5,"lon":-78.06667,"mae":12.41,"modelo":"AIFS025","n":112,"nombre":"Pastaza","rating":2.99,"region":"Amazonia","rmse":20.89}],"metricas":{"calif_media":6.0,"estaciones":71,"mas_ganador":"AIFS025"},"modo":"quantification","ranking":[{"bias":-1.87,"color":"#009E73","confianza":"Alta","corr":0.29,"estaciones":71,"familia":"Convencionales","mae":5.11,"modelo":"ICON","n":224,"rating":5.6,"rmse":10.07},{"bias":-0.41,"color":"#004E89","confianza":"Alta","corr":0.31,"estaciones":71,"familia":"Convencionales","mae":5.67,"modelo":"IFSHRES","n":214,"rating":5.36,"rmse":10.34},{"bias":0.06,"color":"#56B4E9","confianza":"Alta","corr":0.33,"estaciones":69,"familia":"Convencionales","mae":6.26,"modelo":"AIFS025","n":98,"rating":5.19,"rmse":10.48},{"bias":0.02,"color":"#E69F00","confianza":"Alta","corr":0.26,"estaciones":71,"familia":"Convencionales","mae":6.01,"modelo":"GFS05","n":224,"rating":5.16,"rmse":10.58},{"bias":0.52,"color":"#0072B2","confianza":"Alta","corr":0.28,"estaciones":71,"familia":"Convencionales","mae":6.44,"modelo":"IFS025","n":224,"rating":5.02,"rmse":11.3}],"sintesis_region":[{"modelo":"AIFS025","region":"Amazonia"},{"modelo":"GFS05","region":"Insular"},{"modelo":"ICON","region":"Interandina"},{"modelo":"AIFS025","region":"Litoral"}],"ventana":"todo"}
