{"advertencias":[{"No":1,"Variable":"RR","area_cumple_pct":18.8,"area_falla_pct":81.2,"celdas_area":727,"con_obs":69,"eventos_pct":15.9,"misses":9,"puntos":130},{"No":2,"Variable":"RR","area_cumple_pct":4.8,"area_falla_pct":95.2,"celdas_area":354,"con_obs":30,"eventos_pct":3.3,"misses":2,"puntos":135},{"No":3,"Variable":"RR","area_cumple_pct":10.7,"area_falla_pct":89.3,"celdas_area":746,"con_obs":79,"eventos_pct":12.7,"misses":2,"puntos":163},{"No":4,"Variable":"RR","area_cumple_pct":33.1,"area_falla_pct":66.9,"celdas_area":933,"con_obs":91,"eventos_pct":20.9,"misses":2,"puntos":184},{"No":5,"Variable":"RR","area_cumple_pct":31.6,"area_falla_pct":68.4,"celdas_area":721,"con_obs":79,"eventos_pct":20.3,"misses":5,"puntos":163},{"No":6,"Variable":"RR","area_cumple_pct":34.8,"area_falla_pct":65.2,"celdas_area":581,"con_obs":38,"eventos_pct":7.9,"misses":23,"puntos":103},{"No":7,"Variable":"RR","area_cumple_pct":17.7,"area_falla_pct":82.3,"celdas_area":616,"con_obs":116,"eventos_pct":8.6,"misses":1,"puntos":168},{"No":9,"Variable":"RR","area_cumple_pct":28.2,"area_falla_pct":71.8,"celdas_area":884,"con_obs":173,"eventos_pct":2.3,"misses":0,"puntos":194},{"No":10,"Variable":"RR","area_cumple_pct":11.4,"area_falla_pct":88.6,"celdas_area":962,"con_obs":169,"eventos_pct":3.0,"misses":0,"puntos":188},{"No":11,"Variable":"RR","area_cumple_pct":27.6,"area_falla_pct":72.4,"celdas_area":1146,"con_obs":176,"eventos_pct":6.2,"misses":0,"puntos":196},{"No":12,"Variable":"RR","area_cumple_pct":28.0,"area_falla_pct":72.0,"celdas_area":824,"con_obs":124,"eventos_pct":10.5,"misses":18,"puntos":148},{"No":13,"Variable":"RR","area_cumple_pct":52.5,"area_falla_pct":47.5,"celdas_area":832,"con_obs":151,"eventos_pct":18.5,"misses":1,"puntos":171},{"No":14,"Variable":"RR","area_cumple_pct":43.2,"area_falla_pct":56.8,"celdas_area":310,"con_obs":86,"eventos_pct":14.0,"misses":19,"puntos":95},{"No":15,"Variable":"RR","area_cumple_pct":25.7,"area_falla_pct":74.3,"celdas_area":385,"con_obs":62,"eventos_pct":12.9,"misses":2,"puntos":68},{"No":16,"Variable":"RR","area_cumple_pct":28.7,"area_falla_pct":71.3,"celdas_area":712,"con_obs":150,"eventos_pct":13.3,"misses":10,"puntos":164},{"No":17,"Variable":"RR","area_cumple_pct":25.0,"area_falla_pct":75.0,"celdas_area":1091,"con_obs":182,"eventos_pct":19.2,"misses":0,"puntos":196},{"No":18,"Variable":"TN","area_cumple_pct":null,"area_falla_pct":null,"celdas_area":0,"con_obs":27,"eventos_pct":14.8,"misses":5,"puntos":48},{"No":19,"Variable":"RR","area_cumple_pct":12.3,"area_falla_pct":87.7,"celdas_area":725,"con_obs":152,"eventos_pct":7.2,"misses":4,"puntos":167},{"No":20,"Variable":"RR","area_cumple_pct":16.8,"area_falla_pct":83.2,"celdas_area":770,"con_obs":138,"eventos_pct":1.4,"misses":0,"puntos":149},{"No":21,"Variable":"TX","area_cumple_pct":null,"area_falla_pct":null,"celdas_area":0,"con_obs":60,"eventos_pct":75.0,"misses":4,"puntos":166},{"No":22,"Variable":"RR","area_cumple_pct":2.3,"area_falla_pct":97.7,"celdas_area":606,"con_obs":81,"eventos_pct":1.2,"misses":0,"puntos":95},{"No":23,"Variable":"TX","area_cumple_pct":null,"area_falla_pct":null,"celdas_area":0,"con_obs":40,"eventos_pct":67.5,"misses":12,"puntos":136},{"No":24,"Variable":"TX","area_cumple_pct":null,"area_falla_pct":null,"celdas_area":0,"con_obs":18,"eventos_pct":77.8,"misses":43,"puntos":94},{"No":25,"Variable":"RR","area_cumple_pct":25.8,"area_falla_pct":74.2,"celdas_area":635,"con_obs":122,"eventos_pct":24.6,"misses":18,"puntos":131},{"No":27,"Variable":"TX","area_cumple_pct":null,"area_falla_pct":null,"celdas_area":0,"con_obs":23,"eventos_pct":69.6,"misses":17,"puntos":105},{"No":28,"Variable":"RR","area_cumple_pct":17.6,"area_falla_pct":82.4,"celdas_area":585,"con_obs":82,"eventos_pct":14.6,"misses":11,"puntos":98},{"No":29,"Variable":"RR","area_cumple_pct":11.1,"area_falla_pct":88.9,"celdas_area":352,"con_obs":85,"eventos_pct":2.4,"misses":16,"puntos":92},{"No":30,"Variable":"RR","area_cumple_pct":26.7,"area_falla_pct":73.3,"celdas_area":460,"con_obs":81,"eventos_pct":3.7,"misses":0,"puntos":89},{"No":31,"Variable":"RR","area_cumple_pct":15.5,"area_falla_pct":84.5,"celdas_area":619,"con_obs":80,"eventos_pct":10.0,"misses":3,"puntos":96}],"crecidas":{"alertas_con_zonas":15,"cubiertos":47,"cubiertos_pct":38.8,"eventos_periodo":121,"no_cubiertos":74,"no_cubiertos_pct":61.2,"por_alerta":[{"cubiertos":0,"eventos":0,"no":1},{"cubiertos":4,"eventos":5,"no":4},{"cubiertos":5,"eventos":12,"no":6},{"cubiertos":1,"eventos":4,"no":7},{"cubiertos":0,"eventos":10,"no":9},{"cubiertos":3,"eventos":6,"no":10},{"cubiertos":3,"eventos":10,"no":12},{"cubiertos":6,"eventos":19,"no":13},{"cubiertos":3,"eventos":4,"no":14},{"cubiertos":14,"eventos":17,"no":15},{"cubiertos":3,"eventos":11,"no":16},{"cubiertos":5,"eventos":15,"no":17},{"cubiertos":0,"eventos":3,"no":20},{"cubiertos":0,"eventos":4,"no":28},{"cubiertos":0,"eventos":1,"no":29}]},"fechas_programa":{"desde":"2026-02-19","hasta":"2026-06-18"},"geometrias_reparadas":149,"hidro":[{"MAE":1.59,"N":172,"fuente":"PERSIANN","peso":2.0,"sesgo":-1.44},{"MAE":3.78,"N":148,"fuente":"CMORPH","peso":1.13,"sesgo":-1.61},{"MAE":4.4,"N":148,"fuente":"PERSIANN-CCS","peso":1.0,"sesgo":-3.34},{"MAE":4.62,"N":177,"fuente":"GSMAP","peso":0.96,"sesgo":-4.32},{"MAE":11.24,"N":4126,"fuente":"IMERG","peso":0.44,"sesgo":5.3},{"MAE":12.75,"N":87,"fuente":"PDIR","peso":0.4,"sesgo":1.5}],"lecturas":{"acierto":{"n":232,"pct":7.6},"correcto_sin_alerta":{"n":null,"nota":"No derivable de las advertencias oficiales: solo se validan puntos DENTRO de los pol\u00edgonos advertidos.","pct":null},"dia_critico":{"acertadas":24,"evaluadas":26,"pct":92.3},"insuficiente":{"n":149,"pct":4.9},"no_alertado":{"n":292,"pct":9.6},"sobredimensionada":{"n":2383,"pct":78.0},"total_puntos":3056},"por_nivel":[{"area_cumple_pct":21.3,"eventos_pct":16.6,"nivel":"Medio","puntos":1460},{"area_cumple_pct":26.1,"eventos_pct":11.9,"nivel":"Alto","puntos":1064},{"area_cumple_pct":38.9,"eventos_pct":5.0,"nivel":"Muy alto","puntos":240}],"ranking":[{"CSI":0.635,"FAR":0.221,"FBI":1.0,"HSS":0.48,"POD":0.775,"acierto_pct":30.0,"aciertos":1244,"cont_a":162,"cont_b":46,"cont_c":47,"cont_d":110,"correcto_sin_alerta":1050,"fuente":"BIAS","insuficientes":394,"modo":"fija","n_eval":4141,"no_alertados":570,"puntaje_pct":6.9,"puntaje_sum":287.6,"sobredimensionadas":883,"variable":"Tmax"},{"CSI":0.588,"FAR":0.172,"FBI":0.81,"HSS":0.469,"POD":0.67,"acierto_pct":34.2,"aciertos":1415,"cont_a":140,"cont_b":29,"cont_c":69,"cont_d":127,"correcto_sin_alerta":1178,"fuente":"CONSENSO","insuficientes":506,"modo":"fija","n_eval":4141,"no_alertados":510,"puntaje_pct":6.9,"puntaje_sum":285.8,"sobredimensionadas":532,"variable":"Tmax"},{"CSI":0.574,"FAR":0.161,"FBI":0.77,"HSS":0.461,"POD":0.646,"acierto_pct":34.0,"aciertos":1410,"cont_a":135,"cont_b":26,"cont_c":74,"cont_d":130,"correcto_sin_alerta":1218,"fuente":"RF","insuficientes":517,"modo":"fija","n_eval":4141,"no_alertados":516,"puntaje_pct":6.9,"puntaje_sum":286.8,"sobredimensionadas":480,"variable":"Tmax"},{"CSI":0.559,"FAR":0.135,"FBI":0.71,"HSS":0.461,"POD":0.612,"acierto_pct":32.4,"aciertos":1341,"cont_a":128,"cont_b":20,"cont_c":81,"cont_d":136,"correcto_sin_alerta":1188,"fuente":"LSTM","insuficientes":516,"modo":"fija","n_eval":4141,"no_alertados":569,"puntaje_pct":6.8,"puntaje_sum":281.4,"sobredimensionadas":527,"variable":"Tmax"},{"CSI":0.556,"FAR":0.184,"FBI":0.78,"HSS":0.428,"POD":0.636,"acierto_pct":33.3,"aciertos":1379,"cont_a":133,"cont_b":30,"cont_c":76,"cont_d":126,"correcto_sin_alerta":1184,"fuente":"GB","insuficientes":529,"modo":"fija","n_eval":4141,"no_alertados":530,"puntaje_pct":6.8,"puntaje_sum":281.6,"sobredimensionadas":519,"variable":"Tmax"},{"CSI":0.5,"FAR":0.311,"FBI":0.94,"HSS":0.252,"POD":0.646,"acierto_pct":32.4,"aciertos":1343,"cont_a":135,"cont_b":61,"cont_c":74,"cont_d":95,"correcto_sin_alerta":1080,"fuente":"CAT","insuficientes":529,"modo":"fija","n_eval":4141,"no_alertados":534,"puntaje_pct":6.4,"puntaje_sum":264.9,"sobredimensionadas":655,"variable":"Tmax"},{"CSI":0.202,"FAR":0.085,"FBI":0.22,"HSS":0.159,"POD":0.206,"acierto_pct":5.1,"aciertos":210,"cont_a":43,"cont_b":4,"cont_c":166,"cont_d":152,"correcto_sin_alerta":1576,"fuente":"GFS","insuficientes":285,"modo":"fija","n_eval":4091,"no_alertados":1973,"puntaje_pct":5.8,"puntaje_sum":237.5,"sobredimensionadas":47,"variable":"Tmax"},{"CSI":0.138,"FAR":0.033,"FBI":0.14,"HSS":0.116,"POD":0.139,"acierto_pct":6.1,"aciertos":253,"cont_a":29,"cont_b":1,"cont_c":180,"cont_d":155,"correcto_sin_alerta":1588,"fuente":"ICON","insuficientes":398,"modo":"fija","n_eval":4117,"no_alertados":1841,"puntaje_pct":5.6,"puntaje_sum":229.1,"sobredimensionadas":37,"variable":"Tmax"},{"CSI":0.114,"FAR":0.04,"FBI":0.12,"HSS":0.094,"POD":0.115,"acierto_pct":5.9,"aciertos":245,"cont_a":24,"cont_b":1,"cont_c":185,"cont_d":155,"correcto_sin_alerta":1584,"fuente":"IFS","insuficientes":367,"modo":"fija","n_eval":4121,"no_alertados":1882,"puntaje_pct":5.5,"puntaje_sum":227.7,"sobredimensionadas":43,"variable":"Tmax"},{"CSI":0.635,"FAR":0.221,"FBI":1.0,"HSS":0.48,"POD":0.775,"acierto_pct":30.0,"aciertos":1244,"cont_a":162,"cont_b":46,"cont_c":47,"cont_d":110,"correcto_sin_alerta":1050,"fuente":"BIAS","insuficientes":394,"modo":"zph","n_eval":4141,"no_alertados":570,"puntaje_pct":6.9,"puntaje_sum":287.6,"sobredimensionadas":883,"variable":"Tmax"},{"CSI":0.588,"FAR":0.172,"FBI":0.81,"HSS":0.469,"POD":0.67,"acierto_pct":34.2,"aciertos":1415,"cont_a":140,"cont_b":29,"cont_c":69,"cont_d":127,"correcto_sin_alerta":1178,"fuente":"CONSENSO","insuficientes":506,"modo":"zph","n_eval":4141,"no_alertados":510,"puntaje_pct":6.9,"puntaje_sum":285.8,"sobredimensionadas":532,"variable":"Tmax"},{"CSI":0.574,"FAR":0.161,"FBI":0.77,"HSS":0.461,"POD":0.646,"acierto_pct":34.0,"aciertos":1410,"cont_a":135,"cont_b":26,"cont_c":74,"cont_d":130,"correcto_sin_alerta":1218,"fuente":"RF","insuficientes":517,"modo":"zph","n_eval":4141,"no_alertados":516,"puntaje_pct":6.9,"puntaje_sum":286.8,"sobredimensionadas":480,"variable":"Tmax"},{"CSI":0.559,"FAR":0.135,"FBI":0.71,"HSS":0.461,"POD":0.612,"acierto_pct":32.4,"aciertos":1341,"cont_a":128,"cont_b":20,"cont_c":81,"cont_d":136,"correcto_sin_alerta":1188,"fuente":"LSTM","insuficientes":516,"modo":"zph","n_eval":4141,"no_alertados":569,"puntaje_pct":6.8,"puntaje_sum":281.4,"sobredimensionadas":527,"variable":"Tmax"},{"CSI":0.556,"FAR":0.184,"FBI":0.78,"HSS":0.428,"POD":0.636,"acierto_pct":33.3,"aciertos":1379,"cont_a":133,"cont_b":30,"cont_c":76,"cont_d":126,"correcto_sin_alerta":1184,"fuente":"GB","insuficientes":529,"modo":"zph","n_eval":4141,"no_alertados":530,"puntaje_pct":6.8,"puntaje_sum":281.6,"sobredimensionadas":519,"variable":"Tmax"},{"CSI":0.5,"FAR":0.311,"FBI":0.94,"HSS":0.252,"POD":0.646,"acierto_pct":32.4,"aciertos":1343,"cont_a":135,"cont_b":61,"cont_c":74,"cont_d":95,"correcto_sin_alerta":1080,"fuente":"CAT","insuficientes":529,"modo":"zph","n_eval":4141,"no_alertados":534,"puntaje_pct":6.4,"puntaje_sum":264.9,"sobredimensionadas":655,"variable":"Tmax"},{"CSI":0.202,"FAR":0.085,"FBI":0.22,"HSS":0.159,"POD":0.206,"acierto_pct":5.1,"aciertos":210,"cont_a":43,"cont_b":4,"cont_c":166,"cont_d":152,"correcto_sin_alerta":1576,"fuente":"GFS","insuficientes":285,"modo":"zph","n_eval":4091,"no_alertados":1973,"puntaje_pct":5.8,"puntaje_sum":237.5,"sobredimensionadas":47,"variable":"Tmax"},{"CSI":0.138,"FAR":0.033,"FBI":0.14,"HSS":0.116,"POD":0.139,"acierto_pct":6.1,"aciertos":253,"cont_a":29,"cont_b":1,"cont_c":180,"cont_d":155,"correcto_sin_alerta":1588,"fuente":"ICON","insuficientes":398,"modo":"zph","n_eval":4117,"no_alertados":1841,"puntaje_pct":5.6,"puntaje_sum":229.1,"sobredimensionadas":37,"variable":"Tmax"},{"CSI":0.114,"FAR":0.04,"FBI":0.12,"HSS":0.094,"POD":0.115,"acierto_pct":5.9,"aciertos":245,"cont_a":24,"cont_b":1,"cont_c":185,"cont_d":155,"correcto_sin_alerta":1584,"fuente":"IFS","insuficientes":367,"modo":"zph","n_eval":4121,"no_alertados":1882,"puntaje_pct":5.5,"puntaje_sum":227.7,"sobredimensionadas":43,"variable":"Tmax"},{"CSI":0.19,"FAR":0.788,"FBI":3.06,"HSS":0.268,"POD":0.647,"acierto_pct":1.3,"aciertos":53,"cont_a":11,"cont_b":41,"cont_c":6,"cont_d":312,"correcto_sin_alerta":3427,"fuente":"IFS","insuficientes":3,"modo":"fija","n_eval":4157,"no_alertados":60,"puntaje_pct":8.4,"puntaje_sum":347.3,"sobredimensionadas":614,"variable":"Tmin"},{"CSI":0.179,"FAR":0.813,"FBI":4.41,"HSS":0.248,"POD":0.824,"acierto_pct":1.0,"aciertos":41,"cont_a":14,"cont_b":61,"cont_c":3,"cont_d":292,"correcto_sin_alerta":3322,"fuente":"GFS","insuficientes":5,"modo":"fija","n_eval":4133,"no_alertados":48,"puntaje_pct":8.2,"puntaje_sum":337.6,"sobredimensionadas":717,"variable":"Tmin"},{"CSI":0.163,"FAR":0.788,"FBI":1.94,"HSS":0.234,"POD":0.412,"acierto_pct":0.9,"aciertos":36,"cont_a":7,"cont_b":26,"cont_c":10,"cont_d":327,"correcto_sin_alerta":3563,"fuente":"ICON","insuficientes":2,"modo":"fija","n_eval":4153,"no_alertados":96,"puntaje_pct":8.5,"puntaje_sum":353.7,"sobredimensionadas":456,"variable":"Tmin"},{"CSI":0.156,"FAR":0.8,"FBI":2.06,"HSS":0.221,"POD":0.412,"acierto_pct":1.0,"aciertos":43,"cont_a":7,"cont_b":28,"cont_c":10,"cont_d":325,"correcto_sin_alerta":3556,"fuente":"CONSENSO","insuficientes":3,"modo":"fija","n_eval":4164,"no_alertados":89,"puntaje_pct":8.5,"puntaje_sum":352.8,"sobredimensionadas":473,"variable":"Tmin"},{"CSI":0.13,"FAR":0.667,"FBI":0.53,"HSS":0.205,"POD":0.176,"acierto_pct":0.1,"aciertos":5,"cont_a":3,"cont_b":6,"cont_c":14,"cont_d":347,"correcto_sin_alerta":4015,"fuente":"CAT","insuficientes":0,"modo":"fija","n_eval":4164,"no_alertados":133,"puntaje_pct":8.6,"puntaje_sum":359.4,"sobredimensionadas":11,"variable":"Tmin"},{"CSI":0.119,"FAR":0.833,"FBI":1.76,"HSS":0.164,"POD":0.294,"acierto_pct":0.7,"aciertos":29,"cont_a":5,"cont_b":25,"cont_c":12,"cont_d":328,"correcto_sin_alerta":3589,"fuente":"BIAS","insuficientes":1,"modo":"fija","n_eval":4164,"no_alertados":105,"puntaje_pct":8.5,"puntaje_sum":352.5,"sobredimensionadas":440,"variable":"Tmin"},{"CSI":0.056,"FAR":0.5,"FBI":0.12,"HSS":0.097,"POD":0.059,"acierto_pct":0.1,"aciertos":6,"cont_a":1,"cont_b":1,"cont_c":16,"cont_d":352,"correcto_sin_alerta":4023,"fuente":"RF","insuficientes":1,"modo":"fija","n_eval":4164,"no_alertados":131,"puntaje_pct":8.6,"puntaje_sum":359.7,"sobredimensionadas":3,"variable":"Tmin"},{"CSI":0.0,"FAR":null,"FBI":0.0,"HSS":0.0,"POD":0.0,"acierto_pct":0.0,"aciertos":0,"cont_a":0,"cont_b":0,"cont_c":17,"cont_d":353,"correcto_sin_alerta":4025,"fuente":"GB","insuficientes":0,"modo":"fija","n_eval":4164,"no_alertados":138,"puntaje_pct":8.6,"puntaje_sum":359.4,"sobredimensionadas":1,"variable":"Tmin"},{"CSI":0.0,"FAR":null,"FBI":0.0,"HSS":0.0,"POD":0.0,"acierto_pct":0.2,"aciertos":7,"cont_a":0,"cont_b":0,"cont_c":17,"cont_d":353,"correcto_sin_alerta":4016,"fuente":"LSTM","insuficientes":2,"modo":"fija","n_eval":4164,"no_alertados":129,"puntaje_pct":8.6,"puntaje_sum":359.4,"sobredimensionadas":10,"variable":"Tmin"},{"CSI":0.19,"FAR":0.788,"FBI":3.06,"HSS":0.268,"POD":0.647,"acierto_pct":1.3,"aciertos":53,"cont_a":11,"cont_b":41,"cont_c":6,"cont_d":312,"correcto_sin_alerta":3427,"fuente":"IFS","insuficientes":3,"modo":"zph","n_eval":4157,"no_alertados":60,"puntaje_pct":8.4,"puntaje_sum":347.3,"sobredimensionadas":614,"variable":"Tmin"},{"CSI":0.179,"FAR":0.813,"FBI":4.41,"HSS":0.248,"POD":0.824,"acierto_pct":1.0,"aciertos":41,"cont_a":14,"cont_b":61,"cont_c":3,"cont_d":292,"correcto_sin_alerta":3322,"fuente":"GFS","insuficientes":5,"modo":"zph","n_eval":4133,"no_alertados":48,"puntaje_pct":8.2,"puntaje_sum":337.6,"sobredimensionadas":717,"variable":"Tmin"},{"CSI":0.163,"FAR":0.788,"FBI":1.94,"HSS":0.234,"POD":0.412,"acierto_pct":0.9,"aciertos":36,"cont_a":7,"cont_b":26,"cont_c":10,"cont_d":327,"correcto_sin_alerta":3563,"fuente":"ICON","insuficientes":2,"modo":"zph","n_eval":4153,"no_alertados":96,"puntaje_pct":8.5,"puntaje_sum":353.7,"sobredimensionadas":456,"variable":"Tmin"},{"CSI":0.156,"FAR":0.8,"FBI":2.06,"HSS":0.221,"POD":0.412,"acierto_pct":1.0,"aciertos":43,"cont_a":7,"cont_b":28,"cont_c":10,"cont_d":325,"correcto_sin_alerta":3556,"fuente":"CONSENSO","insuficientes":3,"modo":"zph","n_eval":4164,"no_alertados":89,"puntaje_pct":8.5,"puntaje_sum":352.8,"sobredimensionadas":473,"variable":"Tmin"},{"CSI":0.13,"FAR":0.667,"FBI":0.53,"HSS":0.205,"POD":0.176,"acierto_pct":0.1,"aciertos":5,"cont_a":3,"cont_b":6,"cont_c":14,"cont_d":347,"correcto_sin_alerta":4015,"fuente":"CAT","insuficientes":0,"modo":"zph","n_eval":4164,"no_alertados":133,"puntaje_pct":8.6,"puntaje_sum":359.4,"sobredimensionadas":11,"variable":"Tmin"},{"CSI":0.119,"FAR":0.833,"FBI":1.76,"HSS":0.164,"POD":0.294,"acierto_pct":0.7,"aciertos":29,"cont_a":5,"cont_b":25,"cont_c":12,"cont_d":328,"correcto_sin_alerta":3589,"fuente":"BIAS","insuficientes":1,"modo":"zph","n_eval":4164,"no_alertados":105,"puntaje_pct":8.5,"puntaje_sum":352.5,"sobredimensionadas":440,"variable":"Tmin"},{"CSI":0.056,"FAR":0.5,"FBI":0.12,"HSS":0.097,"POD":0.059,"acierto_pct":0.1,"aciertos":6,"cont_a":1,"cont_b":1,"cont_c":16,"cont_d":352,"correcto_sin_alerta":4023,"fuente":"RF","insuficientes":1,"modo":"zph","n_eval":4164,"no_alertados":131,"puntaje_pct":8.6,"puntaje_sum":359.7,"sobredimensionadas":3,"variable":"Tmin"},{"CSI":0.0,"FAR":null,"FBI":0.0,"HSS":0.0,"POD":0.0,"acierto_pct":0.0,"aciertos":0,"cont_a":0,"cont_b":0,"cont_c":17,"cont_d":353,"correcto_sin_alerta":4025,"fuente":"GB","insuficientes":0,"modo":"zph","n_eval":4164,"no_alertados":138,"puntaje_pct":8.6,"puntaje_sum":359.4,"sobredimensionadas":1,"variable":"Tmin"},{"CSI":0.0,"FAR":null,"FBI":0.0,"HSS":0.0,"POD":0.0,"acierto_pct":0.2,"aciertos":7,"cont_a":0,"cont_b":0,"cont_c":17,"cont_d":353,"correcto_sin_alerta":4016,"fuente":"LSTM","insuficientes":2,"modo":"zph","n_eval":4164,"no_alertados":129,"puntaje_pct":8.6,"puntaje_sum":359.4,"sobredimensionadas":10,"variable":"Tmin"},{"CSI":0.286,"FAR":0.524,"FBI":0.88,"HSS":0.392,"POD":0.417,"acierto_pct":2.2,"aciertos":160,"cont_a":30,"cont_b":33,"cont_c":42,"cont_d":671,"correcto_sin_alerta":6075,"fuente":"RF","insuficientes":199,"modo":"fija","n_eval":7378,"no_alertados":528,"puntaje_pct":9.8,"puntaje_sum":719.7,"sobredimensionadas":416,"variable":"precip"},{"CSI":0.246,"FAR":0.653,"FBI":1.32,"HSS":0.324,"POD":0.458,"acierto_pct":1.8,"aciertos":130,"cont_a":33,"cont_b":62,"cont_c":39,"cont_d":642,"correcto_sin_alerta":6050,"fuente":"LSTM","insuficientes":170,"modo":"fija","n_eval":7378,"no_alertados":588,"puntaje_pct":9.7,"puntaje_sum":712.1,"sobredimensionadas":440,"variable":"precip"},{"CSI":0.244,"FAR":0.704,"FBI":1.97,"HSS":0.307,"POD":0.583,"acierto_pct":2.2,"aciertos":159,"cont_a":42,"cont_b":100,"cont_c":30,"cont_d":604,"correcto_sin_alerta":5854,"fuente":"CONSENSO","insuficientes":203,"modo":"fija","n_eval":7378,"no_alertados":503,"puntaje_pct":9.5,"puntaje_sum":703.4,"sobredimensionadas":659,"variable":"precip"},{"CSI":0.233,"FAR":0.62,"FBI":0.99,"HSS":0.314,"POD":0.375,"acierto_pct":1.7,"aciertos":127,"cont_a":27,"cont_b":44,"cont_c":45,"cont_d":660,"correcto_sin_alerta":6058,"fuente":"GB","insuficientes":183,"modo":"fija","n_eval":7378,"no_alertados":582,"puntaje_pct":9.7,"puntaje_sum":715.4,"sobredimensionadas":428,"variable":"precip"},{"CSI":0.231,"FAR":0.726,"FBI":2.18,"HSS":0.285,"POD":0.597,"acierto_pct":2.3,"aciertos":170,"cont_a":43,"cont_b":114,"cont_c":29,"cont_d":590,"correcto_sin_alerta":5840,"fuente":"BIAS","insuficientes":186,"modo":"fija","n_eval":7378,"no_alertados":524,"puntaje_pct":9.5,"puntaje_sum":697.8,"sobredimensionadas":658,"variable":"precip"},{"CSI":0.229,"FAR":0.663,"FBI":1.24,"HSS":0.301,"POD":0.417,"acierto_pct":1.4,"aciertos":104,"cont_a":30,"cont_b":59,"cont_c":42,"cont_d":645,"correcto_sin_alerta":5990,"fuente":"CAT","insuficientes":258,"modo":"fija","n_eval":7378,"no_alertados":566,"puntaje_pct":9.6,"puntaje_sum":710.9,"sobredimensionadas":460,"variable":"precip"},{"CSI":0.188,"FAR":0.656,"FBI":0.85,"HSS":0.249,"POD":0.292,"acierto_pct":1.8,"aciertos":134,"cont_a":21,"cont_b":40,"cont_c":51,"cont_d":635,"correcto_sin_alerta":5904,"fuente":"ICON","insuficientes":142,"modo":"fija","n_eval":7349,"no_alertados":585,"puntaje_pct":9.3,"puntaje_sum":683.1,"sobredimensionadas":584,"variable":"precip"},{"CSI":0.168,"FAR":0.815,"FBI":3.44,"HSS":0.168,"POD":0.639,"acierto_pct":2.3,"aciertos":172,"cont_a":46,"cont_b":202,"cont_c":26,"cont_d":502,"correcto_sin_alerta":5327,"fuente":"GFS","insuficientes":165,"modo":"fija","n_eval":7378,"no_alertados":491,"puntaje_pct":8.7,"puntaje_sum":644.8,"sobredimensionadas":1223,"variable":"precip"},{"CSI":0.14,"FAR":0.84,"FBI":3.31,"HSS":0.12,"POD":0.528,"acierto_pct":2.8,"aciertos":207,"cont_a":38,"cont_b":200,"cont_c":34,"cont_d":504,"correcto_sin_alerta":5094,"fuente":"IFS","insuficientes":181,"modo":"fija","n_eval":7378,"no_alertados":401,"puntaje_pct":8.9,"puntaje_sum":654.8,"sobredimensionadas":1495,"variable":"precip"},{"CSI":0.178,"FAR":0.429,"FBI":0.36,"HSS":0.283,"POD":0.205,"acierto_pct":0.7,"aciertos":51,"cont_a":8,"cont_b":6,"cont_c":31,"cont_d":731,"correcto_sin_alerta":6635,"fuente":"RF","insuficientes":69,"modo":"zph","n_eval":7378,"no_alertados":503,"puntaje_pct":10.2,"puntaje_sum":749.4,"sobredimensionadas":120,"variable":"precip"},{"CSI":0.157,"FAR":0.6,"FBI":0.51,"HSS":0.245,"POD":0.205,"acierto_pct":0.7,"aciertos":54,"cont_a":8,"cont_b":12,"cont_c":31,"cont_d":725,"correcto_sin_alerta":6561,"fuente":"CONSENSO","insuficientes":61,"modo":"zph","n_eval":7378,"no_alertados":506,"puntaje_pct":10.1,"puntaje_sum":748.4,"sobredimensionadas":196,"variable":"precip"},{"CSI":0.154,"FAR":0.619,"FBI":0.54,"HSS":0.24,"POD":0.205,"acierto_pct":0.7,"aciertos":51,"cont_a":8,"cont_b":13,"cont_c":31,"cont_d":724,"correcto_sin_alerta":6566,"fuente":"BIAS","insuficientes":54,"modo":"zph","n_eval":7378,"no_alertados":512,"puntaje_pct":10.1,"puntaje_sum":746.7,"sobredimensionadas":195,"variable":"precip"},{"CSI":0.149,"FAR":0.533,"FBI":0.38,"HSS":0.238,"POD":0.179,"acierto_pct":0.4,"aciertos":32,"cont_a":7,"cont_b":8,"cont_c":32,"cont_d":729,"correcto_sin_alerta":6630,"fuente":"GB","insuficientes":54,"modo":"zph","n_eval":7378,"no_alertados":540,"puntaje_pct":10.1,"puntaje_sum":748.4,"sobredimensionadas":122,"variable":"precip"},{"CSI":0.149,"FAR":0.833,"FBI":3.54,"HSS":0.197,"POD":0.59,"acierto_pct":0.9,"aciertos":66,"cont_a":23,"cont_b":115,"cont_c":16,"cont_d":622,"correcto_sin_alerta":6264,"fuente":"GFS","insuficientes":64,"modo":"zph","n_eval":7378,"no_alertados":473,"puntaje_pct":9.6,"puntaje_sum":709.2,"sobredimensionadas":511,"variable":"precip"},{"CSI":0.129,"FAR":0.807,"FBI":1.46,"HSS":0.18,"POD":0.282,"acierto_pct":1.2,"aciertos":90,"cont_a":11,"cont_b":46,"cont_c":28,"cont_d":691,"correcto_sin_alerta":6100,"fuente":"IFS","insuficientes":71,"modo":"zph","n_eval":7378,"no_alertados":434,"puntaje_pct":10.0,"puntaje_sum":736.8,"sobredimensionadas":683,"variable":"precip"},{"CSI":0.119,"FAR":0.375,"FBI":0.21,"HSS":0.199,"POD":0.128,"acierto_pct":0.2,"aciertos":14,"cont_a":5,"cont_b":3,"cont_c":34,"cont_d":734,"correcto_sin_alerta":6701,"fuente":"CAT","insuficientes":16,"modo":"zph","n_eval":7378,"no_alertados":596,"puntaje_pct":10.2,"puntaje_sum":748.9,"sobredimensionadas":51,"variable":"precip"},{"CSI":0.104,"FAR":0.643,"FBI":0.36,"HSS":0.166,"POD":0.128,"acierto_pct":0.5,"aciertos":40,"cont_a":5,"cont_b":9,"cont_c":34,"cont_d":699,"correcto_sin_alerta":6474,"fuente":"ICON","insuficientes":46,"modo":"zph","n_eval":7349,"no_alertados":520,"puntaje_pct":9.7,"puntaje_sum":716.1,"sobredimensionadas":269,"variable":"precip"},{"CSI":0.087,"FAR":0.636,"FBI":0.28,"HSS":0.141,"POD":0.103,"acierto_pct":0.5,"aciertos":37,"cont_a":4,"cont_b":7,"cont_c":35,"cont_d":730,"correcto_sin_alerta":6621,"fuente":"LSTM","insuficientes":52,"modo":"zph","n_eval":7378,"no_alertados":534,"puntaje_pct":10.1,"puntaje_sum":746.9,"sobredimensionadas":134,"variable":"precip"}],"serie_oficial":[{"area_cumple_pct":18.8,"eventos_pct":15.9,"fecha":"2026-01-04","no":1,"variable":"RR"},{"area_cumple_pct":4.8,"eventos_pct":3.3,"fecha":"2026-01-09","no":2,"variable":"RR"},{"area_cumple_pct":10.7,"eventos_pct":12.7,"fecha":"2026-01-12","no":3,"variable":"RR"},{"area_cumple_pct":33.1,"eventos_pct":20.9,"fecha":"2026-01-21","no":4,"variable":"RR"},{"area_cumple_pct":31.6,"eventos_pct":20.3,"fecha":"2026-01-26","no":5,"variable":"RR"},{"area_cumple_pct":34.8,"eventos_pct":7.9,"fecha":"2026-01-28","no":6,"variable":"RR"},{"area_cumple_pct":17.7,"eventos_pct":8.6,"fecha":"2026-01-31","no":7,"variable":"RR"},{"area_cumple_pct":28.2,"eventos_pct":2.3,"fecha":"2026-02-05","no":9,"variable":"RR"},{"area_cumple_pct":11.4,"eventos_pct":3.0,"fecha":"2026-02-11","no":10,"variable":"RR"},{"area_cumple_pct":27.6,"eventos_pct":6.2,"fecha":"2026-02-15","no":11,"variable":"RR"},{"area_cumple_pct":28.0,"eventos_pct":10.5,"fecha":"2026-02-19","no":12,"variable":"RR"},{"area_cumple_pct":52.5,"eventos_pct":18.5,"fecha":"2026-02-22","no":13,"variable":"RR"},{"area_cumple_pct":43.2,"eventos_pct":14.0,"fecha":"2026-02-26","no":14,"variable":"RR"},{"area_cumple_pct":25.7,"eventos_pct":12.9,"fecha":"2026-03-02","no":15,"variable":"RR"},{"area_cumple_pct":28.7,"eventos_pct":13.3,"fecha":"2026-03-08","no":16,"variable":"RR"},{"area_cumple_pct":25.0,"eventos_pct":19.2,"fecha":"2026-03-10","no":17,"variable":"RR"},{"area_cumple_pct":null,"eventos_pct":14.8,"fecha":"2026-03-19","no":18,"variable":"TN"},{"area_cumple_pct":12.3,"eventos_pct":7.2,"fecha":"2026-03-23","no":19,"variable":"RR"},{"area_cumple_pct":16.8,"eventos_pct":1.4,"fecha":"2026-03-29","no":20,"variable":"RR"},{"area_cumple_pct":null,"eventos_pct":75.0,"fecha":"2026-04-01","no":21,"variable":"TX"},{"area_cumple_pct":2.3,"eventos_pct":1.2,"fecha":"2026-04-03","no":22,"variable":"RR"},{"area_cumple_pct":null,"eventos_pct":67.5,"fecha":"2026-04-10","no":23,"variable":"TX"},{"area_cumple_pct":null,"eventos_pct":77.8,"fecha":"2026-04-13","no":24,"variable":"TX"},{"area_cumple_pct":25.8,"eventos_pct":24.6,"fecha":"2026-04-14","no":25,"variable":"RR"},{"area_cumple_pct":17.6,"eventos_pct":14.6,"fecha":"2026-04-18","no":28,"variable":"RR"},{"area_cumple_pct":null,"eventos_pct":69.6,"fecha":"2026-04-19","no":27,"variable":"TX"},{"area_cumple_pct":11.1,"eventos_pct":2.4,"fecha":"2026-04-22","no":29,"variable":"RR"},{"area_cumple_pct":26.7,"eventos_pct":3.7,"fecha":"2026-04-26","no":30,"variable":"RR"},{"area_cumple_pct":15.5,"eventos_pct":10.0,"fecha":"2026-04-30","no":31,"variable":"RR"}],"totales":{"area_prom":22.9,"eventos_prom":19.3,"falla_prom":77.1,"n":29}}
