{"calibrado":false,"cobertura":"Cartas calibradas (BIAS/RF/GB/CAT/LSTM) muestreadas en la estaci\u00f3n, con hist\u00f3rico extra\u00eddo a punto (_GR).","codigo":"84226","es_precip":false,"fuente_datos":"cartas","hoy":"2026-07-31","metricas":[],"metricas_ventanas":[{"fuente":"BIAS (malla)","ventanas":{"30d":{"bias":0.81,"mae":0.81,"n":1},"365d":{"bias":1.25,"mae":1.39,"n":119},"7d":null,"hist":{"bias":1.25,"mae":1.39,"n":119}}},{"fuente":"CAT (malla)","ventanas":{"30d":{"bias":1.21,"mae":1.21,"n":1},"365d":{"bias":1.23,"mae":1.43,"n":119},"7d":null,"hist":{"bias":1.23,"mae":1.43,"n":119}}},{"fuente":"GB (malla)","ventanas":{"30d":{"bias":1.02,"mae":1.02,"n":1},"365d":{"bias":1.25,"mae":1.46,"n":119},"7d":null,"hist":{"bias":1.25,"mae":1.46,"n":119}}},{"fuente":"LSTM (malla)","ventanas":{"30d":{"bias":1.46,"mae":1.46,"n":1},"365d":{"bias":1.27,"mae":1.43,"n":119},"7d":null,"hist":{"bias":1.27,"mae":1.43,"n":119}}},{"fuente":"RF (malla)","ventanas":{"30d":{"bias":1.52,"mae":1.52,"n":1},"365d":{"bias":1.28,"mae":1.43,"n":119},"7d":null,"hist":{"bias":1.28,"mae":1.43,"n":119}}}],"orden":[],"ranking":[],"tipo":"lineas","tipo_modelos":"calibrado","trazas":[{"cliponaxis":false,"hovertemplate":"<b>Observado</b><br>%{x}: %{y:.1f} \u00b0C<extra></extra>","line":{"color":"#101418","width":2.4},"marker":{"color":"#101418","line":{"color":"#ffffff","width":1},"size":7,"symbol":"circle"},"mode":"lines+markers+text","name":"Observado","text":["9.8"],"textfont":{"color":"#101418","size":9},"textposition":"top center","type":"scatter","x":["2026-07-31"],"y":[9.8]}],"unidad":"\u00b0C","variable":"Tmin"}
