{"codigo":"84163","es_precip":false,"orden":["GFS","IFS HRES"],"periodo":12,"subdiario":true,"tipo":"lineas","trazas":[{"_calif":null,"hovertemplate":"<b>GFS</b><br>%{x}: %{y:.1f}<extra></extra>","line":{"color":"#1f77b4","width":1.9},"marker":{"color":"#1f77b4","size":4},"mode":"lines+markers","name":"GFS","opacity":0.85,"type":"scatter","x":["2026-06-30T07:00-05:00","2026-06-30T19:00-05:00","2026-07-01T07:00-05:00","2026-07-01T19:00-05:00","2026-07-02T07:00-05:00","2026-07-02T19:00-05:00","2026-07-03T07:00-05:00","2026-07-03T19:00-05:00","2026-07-04T07:00-05:00","2026-07-04T19:00-05:00"],"y":[40.4,52.0,42.6,54.5,100.0,100.0,62.1,61.8,100.0,89.3]},{"_calif":null,"hovertemplate":"<b>IFS HRES</b><br>%{x}: %{y:.1f}<extra></extra>","line":{"color":"#8c564b","width":1.9},"marker":{"color":"#8c564b","size":4},"mode":"lines+markers","name":"IFS HRES","opacity":0.85,"type":"scatter","x":["2026-06-30T07:00-05:00","2026-06-30T19:00-05:00","2026-07-01T07:00-05:00","2026-07-01T19:00-05:00","2026-07-02T07:00-05:00","2026-07-02T19:00-05:00","2026-07-03T07:00-05:00","2026-07-03T19:00-05:00","2026-07-04T07:00-05:00","2026-07-04T19:00-05:00"],"y":[28.03,31.73,36.1,54.41,92.84,84.54,69.82,88.05,100.0,68.09]}],"unidad":"%"}
