{"codigo":"M1040","es_precip":false,"orden":["GFS","ICON","IFS HRES"],"periodo":12,"subdiario":true,"tipo":"lineas","trazas":[{"_calif":null,"hovertemplate":"<b>GFS</b><br>%{x}: %{y:.1f}<extra></extra>","line":{"color":"#1f77b4","width":1.9},"marker":{"color":"#1f77b4","size":4},"mode":"lines+markers","name":"GFS","opacity":0.85,"type":"scatter","x":["2026-07-01T07:00-05:00","2026-07-01T19:00-05:00","2026-07-02T07:00-05:00","2026-07-02T19:00-05:00","2026-07-03T07:00-05:00","2026-07-03T19:00-05:00","2026-07-04T07:00-05:00","2026-07-04T19:00-05:00","2026-07-05T07:00-05:00","2026-07-05T19:00-05:00"],"y":[38.4,56.1,44.9,54.3,40.8,38.5,93.8,91.9,75.7,74.5]},{"_calif":null,"hovertemplate":"<b>ICON</b><br>%{x}: %{y:.1f}<extra></extra>","line":{"color":"#2ca02c","width":1.9},"marker":{"color":"#2ca02c","size":4},"mode":"lines+markers","name":"ICON","opacity":0.85,"type":"scatter","x":["2026-06-30T19:00-05:00","2026-07-01T07:00-05:00","2026-07-01T19:00-05:00","2026-07-02T07:00-05:00","2026-07-02T19:00-05:00","2026-07-03T07:00-05:00"],"y":[23.81,26.31,41.84,40.1,51.14,25.88]},{"_calif":null,"hovertemplate":"<b>IFS HRES</b><br>%{x}: %{y:.1f}<extra></extra>","line":{"color":"#8c564b","width":1.9},"marker":{"color":"#8c564b","size":4},"mode":"lines+markers","name":"IFS HRES","opacity":0.85,"type":"scatter","x":["2026-07-01T07:00-05:00","2026-07-01T19:00-05:00","2026-07-02T07:00-05:00","2026-07-02T19:00-05:00","2026-07-03T07:00-05:00","2026-07-03T19:00-05:00","2026-07-04T07:00-05:00","2026-07-04T19:00-05:00","2026-07-05T07:00-05:00","2026-07-05T19:00-05:00"],"y":[43.43,47.35,31.74,36.92,35.97,41.94,70.39,84.1,100.0,36.53]}],"unidad":"%"}
