{"codigo":"84226","es_precip":false,"orden":["AIFS","GFS","ICON","IFS ENS","IFS HRES"],"periodo":24,"subdiario":true,"tipo":"lineas","trazas":[{"_calif":null,"hovertemplate":"<b>AIFS</b><br>%{x}: %{y:.1f}<extra></extra>","line":{"color":"#e377c2","width":1.9},"marker":{"color":"#e377c2","size":4},"mode":"lines+markers","name":"AIFS","opacity":0.85,"type":"scatter","x":["2026-07-01T07:00-05:00","2026-07-02T07:00-05:00","2026-07-03T07:00-05:00","2026-07-04T07:00-05:00","2026-07-05T07:00-05:00"],"y":[11.56,15.39,15.13,14.81,15.21]},{"_calif":null,"hovertemplate":"<b>GFS</b><br>%{x}: %{y:.1f}<extra></extra>","line":{"color":"#1f77b4","width":1.9},"marker":{"color":"#1f77b4","size":4},"mode":"lines+markers","name":"GFS","opacity":0.85,"type":"scatter","x":["2026-07-01T07:00-05:00","2026-07-02T07:00-05:00","2026-07-03T07:00-05:00","2026-07-04T07:00-05:00","2026-07-05T07:00-05:00"],"y":[10.85,13.33,11.32,11.21,10.98]},{"_calif":null,"hovertemplate":"<b>ICON</b><br>%{x}: %{y:.1f}<extra></extra>","line":{"color":"#2ca02c","width":1.9},"marker":{"color":"#2ca02c","size":4},"mode":"lines+markers","name":"ICON","opacity":0.85,"type":"scatter","x":["2026-07-01T07:00-05:00","2026-07-02T07:00-05:00","2026-07-03T07:00-05:00"],"y":[17.33,15.43,14.92]},{"_calif":null,"hovertemplate":"<b>IFS ENS</b><br>%{x}: %{y:.1f}<extra></extra>","line":{"color":"#d62728","width":1.9},"marker":{"color":"#d62728","size":4},"mode":"lines+markers","name":"IFS ENS","opacity":0.85,"type":"scatter","x":["2026-07-01T07:00-05:00","2026-07-02T07:00-05:00","2026-07-03T07:00-05:00","2026-07-04T07:00-05:00","2026-07-05T07:00-05:00"],"y":[14.92,15.58,14.44,14.05,14.19]},{"_calif":null,"hovertemplate":"<b>IFS HRES</b><br>%{x}: %{y:.1f}<extra></extra>","line":{"color":"#8c564b","width":1.9},"marker":{"color":"#8c564b","size":4},"mode":"lines+markers","name":"IFS HRES","opacity":0.85,"type":"scatter","x":["2026-07-01T07:00-05:00","2026-07-02T07:00-05:00","2026-07-03T07:00-05:00","2026-07-04T07:00-05:00","2026-07-05T07:00-05:00"],"y":[11.11,14.95,13.84,13.91,13.47]}],"unidad":"\u00b0C"}
