{"bloque":"precip_cua","codigo":"CP04","met_cols":["mae","rmse","bias","corr"],"modelos":[{"bias":0.43,"califica":true,"color":"#A65628","confianza":"Alta","corr":0.69,"familia":"Postprocesamiento","mae":1.84,"modelo":"BC_CLASSIC_METEOBLUE","n":30,"rating":8.03,"rmse":2.43},{"bias":-0.05,"califica":true,"color":"#0072B2","confianza":"Baja","corr":0.45,"familia":"ML","mae":1.81,"modelo":"ML_RF","n":11,"rating":7.91,"rmse":2.56},{"bias":0.35,"califica":true,"color":"#4DAF4A","confianza":"Alta","corr":0.63,"familia":"Postprocesamiento","mae":2.04,"modelo":"QM_AIFS025","n":30,"rating":7.88,"rmse":2.6},{"bias":-0.2,"califica":true,"color":"#CC79A7","confianza":"Baja","corr":0.43,"familia":"ML","mae":1.76,"modelo":"ML_ET","n":11,"rating":7.86,"rmse":2.6},{"bias":-0.13,"califica":true,"color":"#648FFF","confianza":"Baja","corr":0.43,"familia":"ML","mae":1.81,"modelo":"HURDLE_RF","n":11,"rating":7.86,"rmse":2.59},{"bias":0.47,"califica":true,"color":"#F781BF","confianza":"Alta","corr":0.61,"familia":"Postprocesamiento","mae":2.13,"modelo":"BC_CLASSIC_AIFS025","n":30,"rating":7.78,"rmse":2.65},{"bias":-0.04,"califica":true,"color":"#A6761D","confianza":"Baja","corr":0.39,"familia":"ML","mae":1.98,"modelo":"ML_GBR","n":11,"rating":7.76,"rmse":2.65},{"bias":0.28,"califica":true,"color":"#E41A1C","confianza":"Alta","corr":0.56,"familia":"ML","mae":2.18,"modelo":"ML_CAT","n":30,"rating":7.73,"rmse":2.75},{"bias":0.25,"califica":true,"color":"#FE6100","confianza":"Alta","corr":0.54,"familia":"ML","mae":2.19,"modelo":"HURDLE_LGBM","n":30,"rating":7.72,"rmse":2.78},{"bias":0.23,"califica":true,"color":"#4DAF4A","confianza":"Alta","corr":0.54,"familia":"ML","mae":2.18,"modelo":"ML_LGBM","n":30,"rating":7.72,"rmse":2.8},{"bias":0.22,"califica":true,"color":"#984EA3","confianza":"Alta","corr":0.53,"familia":"ML","mae":2.2,"modelo":"ML_HUBER","n":30,"rating":7.7,"rmse":2.84},{"bias":0.34,"califica":true,"color":"#FF7F00","confianza":"Alta","corr":0.54,"familia":"ML","mae":2.2,"modelo":"ML_ELASTICNET","n":30,"rating":7.68,"rmse":2.81},{"bias":0.29,"califica":true,"color":"#999933","confianza":"Alta","corr":0.53,"familia":"ML","mae":2.23,"modelo":"HURDLE_CAT","n":30,"rating":7.67,"rmse":2.83},{"bias":0.35,"califica":true,"color":"#377EB8","confianza":"Alta","corr":0.54,"familia":"ML","mae":2.21,"modelo":"ML_RIDGE","n":30,"rating":7.67,"rmse":2.81},{"bias":0.28,"califica":true,"color":"#F781BF","confianza":"Alta","corr":0.52,"familia":"ML","mae":2.23,"modelo":"HURDLE_XGB","n":30,"rating":7.67,"rmse":2.84},{"bias":0.53,"califica":true,"color":"#0072B2","confianza":"Alta","corr":0.53,"familia":"Convencionales","mae":1.94,"modelo":"IFS025","n":30,"rating":7.66,"rmse":3.3},{"bias":0.38,"califica":true,"color":"#E41A1C","confianza":"Alta","corr":0.53,"familia":"ML","mae":2.23,"modelo":"HURDLE_LOGIT_RIDGE","n":30,"rating":7.65,"rmse":2.84},{"bias":0.16,"califica":true,"color":"#E7298A","confianza":"Alta","corr":0.49,"familia":"Postprocesamiento","mae":2.27,"modelo":"BC_CLASSIC_GFS05","n":30,"rating":7.63,"rmse":2.94},{"bias":-0.13,"califica":true,"color":"#FF7F00","confianza":"Baja","corr":0.28,"familia":"ML","mae":1.96,"modelo":"ML_HGB","n":11,"rating":7.62,"rmse":2.78},{"bias":0.3,"califica":true,"color":"#DC267F","confianza":"Alta","corr":0.51,"familia":"ML","mae":2.29,"modelo":"ML_XGB","n":30,"rating":7.62,"rmse":2.88},{"bias":-0.13,"califica":true,"color":"#FDBF6F","confianza":"Alta","corr":0.47,"familia":"Postprocesamiento","mae":2.22,"modelo":"QM_GFS05","n":30,"rating":7.62,"rmse":3.07},{"bias":0.74,"califica":true,"color":"#17A398","confianza":"Alta","corr":0.58,"familia":"Postprocesamiento","mae":2.18,"modelo":"ENS_MEDIAN","n":30,"rating":7.62,"rmse":2.89},{"bias":0.45,"califica":true,"color":"#111111","confianza":"Alta","corr":0.52,"familia":"Postprocesamiento","mae":2.3,"modelo":"BEST_OP_CV","n":30,"rating":7.56,"rmse":2.96},{"bias":0.86,"califica":true,"color":"#1B3A6B","confianza":"Alta","corr":0.57,"familia":"Postprocesamiento","mae":2.29,"modelo":"CONSENSO_OP_TOP10","n":30,"rating":7.53,"rmse":2.89},{"bias":1.15,"califica":true,"color":"#56B4E9","confianza":"Alta","corr":0.57,"familia":"Convencionales","mae":2.44,"modelo":"AIFS025","n":30,"rating":7.36,"rmse":3.12},{"bias":0.67,"califica":true,"color":"#648FFF","confianza":"Alta","corr":0.46,"familia":"Postprocesamiento","mae":2.4,"modelo":"BC_CLASSIC_IFSHRES","n":30,"rating":7.36,"rmse":3.28},{"bias":-0.42,"califica":true,"color":"#E69F00","confianza":"Alta","corr":0.35,"familia":"Convencionales","mae":2.37,"modelo":"GFS05","n":30,"rating":7.28,"rmse":3.62},{"bias":0.71,"califica":true,"color":"#1B9E77","confianza":"Alta","corr":0.36,"familia":"Postprocesamiento","mae":2.63,"modelo":"BC_CLASSIC_IFS025","n":30,"rating":7.08,"rmse":3.78},{"bias":1.64,"califica":true,"color":"#004E89","confianza":"Alta","corr":0.48,"familia":"Convencionales","mae":2.55,"modelo":"IFSHRES","n":30,"rating":7.0,"rmse":3.92},{"bias":1.64,"califica":true,"color":"#1F78B4","confianza":"Alta","corr":0.62,"familia":"Postprocesamiento","mae":2.92,"modelo":"QM_METEOBLUE","n":30,"rating":6.96,"rmse":4.01},{"bias":-2.33,"califica":true,"color":"#DC267F","confianza":"Alta","corr":0.28,"familia":"No convencionales","mae":2.35,"modelo":"NEMSGLOBAL_E","n":30,"rating":6.79,"rmse":3.84},{"bias":1.57,"califica":true,"color":"#E41A1C","confianza":"Alta","corr":0.37,"familia":"Postprocesamiento","mae":2.84,"modelo":"QM_IFSHRES","n":30,"rating":6.69,"rmse":4.6},{"bias":-2.29,"califica":true,"color":"#00A9A5","confianza":"Alta","corr":0.1,"familia":"No convencionales","mae":2.31,"modelo":"NEMSGLOBAL","n":30,"rating":6.65,"rmse":3.91},{"bias":1.11,"califica":true,"color":"#7570B3","confianza":"Alta","corr":0.19,"familia":"Postprocesamiento","mae":2.93,"modelo":"BC_CLASSIC_ICON","n":30,"rating":6.5,"rmse":5.22},{"bias":2.68,"califica":true,"color":"#8A2BE2","confianza":"Alta","corr":0.5,"familia":"Postprocesamiento","mae":3.43,"modelo":"ENS_MEAN","n":30,"rating":6.46,"rmse":4.18},{"bias":1.61,"califica":true,"color":"#A6761D","confianza":"Alta","corr":0.6,"familia":"No convencionales","mae":3.57,"modelo":"NEMSSA","n":30,"rating":6.43,"rmse":5.95},{"bias":1.02,"califica":true,"color":"#B2DF8A","confianza":"Alta","corr":0.17,"familia":"Postprocesamiento","mae":2.97,"modelo":"QM_IFS025","n":30,"rating":6.4,"rmse":5.77},{"bias":1.59,"califica":true,"color":"#785EF0","confianza":"Alta","corr":0.15,"familia":"No convencionales","mae":3.48,"modelo":"MFGLOBAL","n":30,"rating":6.13,"rmse":5.45},{"bias":1.06,"califica":true,"color":"#009E73","confianza":"Alta","corr":0.04,"familia":"Convencionales","mae":3.86,"modelo":"ICON","n":30,"rating":5.71,"rmse":7.87},{"bias":3.78,"califica":true,"color":"#6A1B9A","confianza":"Alta","corr":0.51,"familia":"Postprocesamiento","mae":5.0,"modelo":"CONSENSO_OP_CAL","n":30,"rating":5.14,"rmse":10.03},{"bias":2.58,"califica":true,"color":"#FB9A99","confianza":"Alta","corr":0.01,"familia":"Postprocesamiento","mae":4.3,"modelo":"QM_ICON","n":30,"rating":4.93,"rmse":11.5},{"bias":5.77,"califica":true,"color":"#D55E00","confianza":"Alta","corr":0.45,"familia":"No convencionales","mae":6.15,"modelo":"METEOBLUE","n":30,"rating":4.87,"rmse":7.58},{"bias":7.79,"califica":true,"color":"#648FFF","confianza":"Alta","corr":0.22,"familia":"No convencionales","mae":8.56,"modelo":"UMGLOBAL10","n":30,"rating":3.72,"rmse":12.08},{"bias":7.05,"califica":true,"color":"#CC79A7","confianza":"Alta","corr":0.15,"familia":"No convencionales","mae":8.48,"modelo":"GEM15","n":30,"rating":3.72,"rmse":12.08},{"bias":11.63,"califica":true,"color":"#B33DC6","confianza":"Media","corr":0.27,"familia":"No convencionales","mae":11.8,"modelo":"SA01","n":28,"rating":3.13,"rmse":15.24}],"modo":"quantification","nombre":"Sevilla","region":"Interandina","resumen":{"calif_media":6.9,"fechas_max":30,"mejor":"BC_CLASSIC_METEOBLUE","mejor_confianza":"Alta","mejor_rating":8.03,"n_califican":45,"n_modelos":45},"ventana":"30"}
