{"bloque":"precip_cua","codigo":"M5021","met_cols":["mae","rmse","bias","corr"],"modelos":[{"bias":-0.85,"califica":true,"color":"#E7298A","confianza":"Media","corr":0.9,"familia":"Postprocesamiento","mae":3.01,"modelo":"BC_CLASSIC_GFS05","n":15,"rating":7.41,"rmse":3.6},{"bias":-0.58,"califica":true,"color":"#1B3A6B","confianza":"Media","corr":0.76,"familia":"Postprocesamiento","mae":3.24,"modelo":"CONSENSO_OP_TOP10","n":15,"rating":7.14,"rmse":4.34},{"bias":-1.77,"califica":true,"color":"#CC79A7","confianza":"Media","corr":0.85,"familia":"No convencionales","mae":3.32,"modelo":"GEM15","n":15,"rating":6.96,"rmse":4.28},{"bias":1.2,"califica":true,"color":"#1B9E77","confianza":"Media","corr":0.82,"familia":"Postprocesamiento","mae":3.84,"modelo":"BC_CLASSIC_IFS025","n":15,"rating":6.84,"rmse":4.45},{"bias":-1.54,"califica":true,"color":"#004E89","confianza":"Media","corr":0.76,"familia":"Convencionales","mae":3.4,"modelo":"IFSHRES","n":15,"rating":6.82,"rmse":4.69},{"bias":0.93,"califica":true,"color":"#D55E00","confianza":"Media","corr":0.72,"familia":"Postprocesamiento","mae":3.92,"modelo":"BC_CLASSIC_AIFS025","n":15,"rating":6.75,"rmse":4.74},{"bias":-2.02,"califica":true,"color":"#B33DC6","confianza":"Media","corr":0.75,"familia":"No convencionales","mae":3.53,"modelo":"SA01","n":15,"rating":6.67,"rmse":4.81},{"bias":-1.09,"califica":true,"color":"#A65628","confianza":"Media","corr":0.7,"familia":"Postprocesamiento","mae":4.01,"modelo":"BC_CLASSIC_METEOBLUE","n":15,"rating":6.65,"rmse":4.83},{"bias":1.89,"califica":true,"color":"#111111","confianza":"Media","corr":0.77,"familia":"Postprocesamiento","mae":3.85,"modelo":"BEST_OP_CV","n":15,"rating":6.63,"rmse":4.66},{"bias":-1.43,"califica":true,"color":"#FF7F00","confianza":"Media","corr":0.72,"familia":"ML","mae":4.0,"modelo":"ML_ELASTICNET","n":15,"rating":6.52,"rmse":5.33},{"bias":-1.29,"califica":true,"color":"#377EB8","confianza":"Media","corr":0.71,"familia":"ML","mae":4.05,"modelo":"ML_RIDGE","n":15,"rating":6.52,"rmse":5.42},{"bias":-3.6,"califica":true,"color":"#E69F00","confianza":"Media","corr":0.91,"familia":"Convencionales","mae":3.77,"modelo":"GFS05","n":15,"rating":6.46,"rmse":4.98},{"bias":-1.65,"califica":true,"color":"#4DAF4A","confianza":"Media","corr":0.66,"familia":"ML","mae":3.94,"modelo":"ML_GBR","n":15,"rating":6.45,"rmse":5.28},{"bias":-2.09,"califica":true,"color":"#999933","confianza":"Media","corr":0.71,"familia":"ML","mae":3.91,"modelo":"HURDLE_CAT","n":15,"rating":6.44,"rmse":5.18},{"bias":2.37,"califica":true,"color":"#E41A1C","confianza":"Media","corr":0.76,"familia":"Postprocesamiento","mae":4.07,"modelo":"BC_CLASSIC_IFSHRES","n":15,"rating":6.43,"rmse":4.93},{"bias":-2.09,"califica":true,"color":"#F781BF","confianza":"Media","corr":0.67,"familia":"ML","mae":3.89,"modelo":"HURDLE_XGB","n":15,"rating":6.39,"rmse":5.32},{"bias":-2.1,"califica":true,"color":"#E69F00","confianza":"Media","corr":0.71,"familia":"ML","mae":3.99,"modelo":"HURDLE_RF","n":15,"rating":6.39,"rmse":5.33},{"bias":-2.05,"califica":true,"color":"#FE6100","confianza":"Media","corr":0.66,"familia":"ML","mae":3.96,"modelo":"HURDLE_LGBM","n":15,"rating":6.36,"rmse":5.34},{"bias":0.84,"califica":true,"color":"#7570B3","confianza":"Media","corr":0.61,"familia":"Postprocesamiento","mae":4.75,"modelo":"BC_CLASSIC_ICON","n":15,"rating":6.3,"rmse":5.61},{"bias":-3.63,"califica":true,"color":"#FDBF6F","confianza":"Media","corr":0.89,"familia":"Postprocesamiento","mae":4.26,"modelo":"QM_GFS05","n":15,"rating":6.29,"rmse":4.99},{"bias":-3.36,"califica":true,"color":"#8A2BE2","confianza":"Media","corr":0.8,"familia":"Postprocesamiento","mae":3.96,"modelo":"ENS_MEAN","n":15,"rating":6.28,"rmse":5.37},{"bias":-2.36,"califica":true,"color":"#00A9A5","confianza":"Media","corr":0.68,"familia":"ML","mae":4.13,"modelo":"ML_RF","n":15,"rating":6.26,"rmse":5.46},{"bias":0.05,"califica":true,"color":"#FE6100","confianza":"Media","corr":0.77,"familia":"Postprocesamiento","mae":5.23,"modelo":"QM_IFSHRES","n":15,"rating":6.2,"rmse":8.19},{"bias":-1.74,"califica":true,"color":"#DC267F","confianza":"Media","corr":0.6,"familia":"ML","mae":4.44,"modelo":"ML_XGB","n":15,"rating":6.18,"rmse":5.65},{"bias":-2.45,"califica":true,"color":"#00A9A5","confianza":"Media","corr":0.65,"familia":"ML","mae":4.2,"modelo":"ML_ET","n":15,"rating":6.17,"rmse":5.67},{"bias":-2.15,"califica":true,"color":"#4DAF4A","confianza":"Media","corr":0.61,"familia":"ML","mae":4.33,"modelo":"ML_LGBM","n":15,"rating":6.14,"rmse":5.7},{"bias":-1.54,"califica":true,"color":"#E41A1C","confianza":"Media","corr":0.55,"familia":"ML","mae":4.4,"modelo":"ML_CAT","n":15,"rating":6.14,"rmse":6.04},{"bias":-2.61,"califica":true,"color":"#648FFF","confianza":"Media","corr":0.66,"familia":"ML","mae":4.26,"modelo":"HURDLE_LOGIT_RIDGE","n":15,"rating":6.1,"rmse":5.87},{"bias":-3.46,"califica":true,"color":"#D55E00","confianza":"Media","corr":0.73,"familia":"No convencionales","mae":4.15,"modelo":"METEOBLUE","n":15,"rating":6.09,"rmse":5.76},{"bias":0.56,"califica":true,"color":"#6A1B9A","confianza":"Media","corr":0.74,"familia":"Postprocesamiento","mae":5.06,"modelo":"CONSENSO_OP_CAL","n":15,"rating":6.07,"rmse":8.45},{"bias":-0.89,"califica":true,"color":"#984EA3","confianza":"Media","corr":0.66,"familia":"ML","mae":5.04,"modelo":"ML_HUBER","n":15,"rating":6.06,"rmse":7.16},{"bias":-3.68,"califica":true,"color":"#56B4E9","confianza":"Media","corr":0.72,"familia":"Convencionales","mae":4.36,"modelo":"AIFS025","n":15,"rating":5.97,"rmse":5.91},{"bias":-2.23,"califica":true,"color":"#F781BF","confianza":"Media","corr":0.53,"familia":"ML","mae":4.52,"modelo":"ML_HGB","n":15,"rating":5.95,"rmse":6.09},{"bias":-4.25,"califica":true,"color":"#0072B2","confianza":"Media","corr":0.82,"familia":"Convencionales","mae":4.57,"modelo":"IFS025","n":15,"rating":5.92,"rmse":6.01},{"bias":-4.25,"califica":true,"color":"#17A398","confianza":"Media","corr":0.8,"familia":"Postprocesamiento","mae":4.58,"modelo":"ENS_MEDIAN","n":15,"rating":5.89,"rmse":6.03},{"bias":-4.12,"califica":true,"color":"#B2DF8A","confianza":"Media","corr":0.79,"familia":"Postprocesamiento","mae":4.84,"modelo":"QM_IFS025","n":15,"rating":5.84,"rmse":5.98},{"bias":-4.29,"califica":true,"color":"#56B4E9","confianza":"Media","corr":0.73,"familia":"Postprocesamiento","mae":4.85,"modelo":"QM_AIFS025","n":15,"rating":5.72,"rmse":6.25},{"bias":-4.44,"califica":true,"color":"#1F78B4","confianza":"Media","corr":0.74,"familia":"Postprocesamiento","mae":4.81,"modelo":"QM_METEOBLUE","n":15,"rating":5.71,"rmse":6.38},{"bias":-1.31,"califica":true,"color":"#A6761D","confianza":"Media","corr":0.58,"familia":"No convencionales","mae":6.08,"modelo":"NEMSSA","n":15,"rating":5.6,"rmse":7.65},{"bias":-4.25,"califica":true,"color":"#FB9A99","confianza":"Media","corr":0.63,"familia":"Postprocesamiento","mae":5.67,"modelo":"QM_ICON","n":15,"rating":5.38,"rmse":6.78},{"bias":4.33,"califica":true,"color":"#648FFF","confianza":"Media","corr":0.73,"familia":"No convencionales","mae":6.15,"modelo":"UMGLOBAL10","n":15,"rating":5.23,"rmse":7.84},{"bias":-6.03,"califica":true,"color":"#009E73","confianza":"Media","corr":0.62,"familia":"Convencionales","mae":6.37,"modelo":"ICON","n":15,"rating":4.89,"rmse":8.16},{"bias":-6.82,"califica":true,"color":"#00A9A5","confianza":"Media","corr":0.12,"familia":"No convencionales","mae":6.82,"modelo":"NEMSGLOBAL","n":15,"rating":4.17,"rmse":9.43},{"bias":-7.93,"califica":true,"color":"#785EF0","confianza":"Media","corr":0.43,"familia":"No convencionales","mae":7.93,"modelo":"MFGLOBAL","n":15,"rating":4.1,"rmse":10.73},{"bias":-6.63,"califica":true,"color":"#984EA3","confianza":"Media","corr":-0.19,"familia":"No convencionales","mae":6.63,"modelo":"NEMSGLOBAL_E","n":15,"rating":3.93,"rmse":9.5}],"modo":"quantification","nombre":"Yura Faccha Oyacachi","region":"Amazonia","resumen":{"calif_media":6.1,"fechas_max":15,"mejor":"BC_CLASSIC_GFS05","mejor_confianza":"Media","mejor_rating":7.41,"n_califican":45,"n_modelos":45},"ventana":"15"}
