{"bloque":"precip_cua","codigo":"M1271","met_cols":["mae","rmse","bias","corr"],"modelos":[{"bias":0.23,"califica":true,"color":"#17A398","confianza":"Alta","corr":0.81,"familia":"Postprocesamiento","mae":0.23,"modelo":"ENS_MEDIAN","n":30,"rating":9.48,"rmse":0.54},{"bias":0.72,"califica":true,"color":"#8A2BE2","confianza":"Alta","corr":0.61,"familia":"Postprocesamiento","mae":0.72,"modelo":"ENS_MEAN","n":30,"rating":8.75,"rmse":1.12},{"bias":0.29,"califica":true,"color":"#FB9A99","confianza":"Alta","corr":0.77,"familia":"Postprocesamiento","mae":3.73,"modelo":"QM_ICON","n":30,"rating":6.31,"rmse":10.81},{"bias":-0.52,"califica":true,"color":"#8A2BE2","confianza":"Alta","corr":0.7,"familia":"Postprocesamiento","mae":3.4,"modelo":"QM_IFSHRES","n":30,"rating":6.23,"rmse":11.84},{"bias":-1.99,"califica":true,"color":"#785EF0","confianza":"Alta","corr":0.87,"familia":"No convencionales","mae":3.06,"modelo":"MFGLOBAL","n":30,"rating":6.1,"rmse":13.06},{"bias":-1.18,"califica":true,"color":"#009E73","confianza":"Alta","corr":0.75,"familia":"Convencionales","mae":3.37,"modelo":"ICON","n":30,"rating":6.07,"rmse":12.67},{"bias":-2.33,"califica":true,"color":"#D55E00","confianza":"Alta","corr":0.71,"familia":"No convencionales","mae":2.76,"modelo":"METEOBLUE","n":30,"rating":5.96,"rmse":13.95},{"bias":-0.07,"califica":true,"color":"#004E89","confianza":"Alta","corr":0.67,"familia":"Convencionales","mae":4.42,"modelo":"IFSHRES","n":30,"rating":5.92,"rmse":12.92},{"bias":-0.17,"califica":true,"color":"#A6761D","confianza":"Alta","corr":0.64,"familia":"Postprocesamiento","mae":4.33,"modelo":"BC_CLASSIC_IFSHRES","n":30,"rating":5.88,"rmse":13.02},{"bias":-1.94,"califica":true,"color":"#1F78B4","confianza":"Alta","corr":0.6,"familia":"Postprocesamiento","mae":2.98,"modelo":"QM_METEOBLUE","n":30,"rating":5.86,"rmse":13.67},{"bias":0.63,"califica":true,"color":"#6A1B9A","confianza":"Alta","corr":0.67,"familia":"Postprocesamiento","mae":4.3,"modelo":"CONSENSO_OP_CAL","n":30,"rating":5.86,"rmse":12.19},{"bias":-0.32,"califica":true,"color":"#E69F00","confianza":"Alta","corr":0.61,"familia":"Convencionales","mae":4.2,"modelo":"GFS05","n":30,"rating":5.84,"rmse":13.25},{"bias":0.39,"califica":true,"color":"#FDBF6F","confianza":"Alta","corr":0.59,"familia":"Postprocesamiento","mae":4.31,"modelo":"QM_GFS05","n":30,"rating":5.76,"rmse":13.48},{"bias":0.21,"califica":true,"color":"#111111","confianza":"Alta","corr":0.65,"familia":"Postprocesamiento","mae":4.75,"modelo":"BEST_OP_CV","n":30,"rating":5.76,"rmse":13.07},{"bias":-2.14,"califica":true,"color":"#B2DF8A","confianza":"Alta","corr":0.66,"familia":"Postprocesamiento","mae":3.49,"modelo":"QM_IFS025","n":30,"rating":5.65,"rmse":14.34},{"bias":0.04,"califica":true,"color":"#1B3A6B","confianza":"Alta","corr":0.56,"familia":"Postprocesamiento","mae":4.83,"modelo":"CONSENSO_OP_TOP10","n":30,"rating":5.65,"rmse":13.82},{"bias":-2.92,"califica":true,"color":"#E41A1C","confianza":"Alta","corr":0.8,"familia":"ML","mae":3.57,"modelo":"ML_CAT","n":30,"rating":5.56,"rmse":15.53},{"bias":-0.11,"califica":true,"color":"#1B9E77","confianza":"Alta","corr":0.53,"familia":"Postprocesamiento","mae":4.95,"modelo":"BC_CLASSIC_IFS025","n":30,"rating":5.54,"rmse":14.43},{"bias":-0.86,"califica":true,"color":"#CC79A7","confianza":"Alta","corr":0.62,"familia":"No convencionales","mae":4.71,"modelo":"GEM15","n":30,"rating":5.52,"rmse":14.14},{"bias":-2.84,"califica":true,"color":"#00A9A5","confianza":"Alta","corr":0.76,"familia":"ML","mae":3.74,"modelo":"ML_HGB","n":30,"rating":5.48,"rmse":15.61},{"bias":-2.82,"califica":true,"color":"#4DAF4A","confianza":"Alta","corr":0.67,"familia":"ML","mae":3.53,"modelo":"ML_LGBM","n":30,"rating":5.47,"rmse":15.53},{"bias":-3.07,"califica":true,"color":"#999933","confianza":"Alta","corr":0.78,"familia":"ML","mae":3.68,"modelo":"HURDLE_CAT","n":30,"rating":5.47,"rmse":15.9},{"bias":-2.85,"califica":true,"color":"#FE6100","confianza":"Alta","corr":0.71,"familia":"ML","mae":3.66,"modelo":"HURDLE_LGBM","n":30,"rating":5.46,"rmse":15.62},{"bias":-0.14,"califica":true,"color":"#0072B2","confianza":"Alta","corr":0.5,"familia":"Convencionales","mae":5.23,"modelo":"IFS025","n":30,"rating":5.43,"rmse":14.61},{"bias":0.68,"califica":true,"color":"#E7298A","confianza":"Alta","corr":0.57,"familia":"Postprocesamiento","mae":5.16,"modelo":"BC_CLASSIC_GFS05","n":30,"rating":5.43,"rmse":13.61},{"bias":-2.9,"califica":true,"color":"#DC267F","confianza":"Alta","corr":0.58,"familia":"ML","mae":3.49,"modelo":"ML_XGB","n":30,"rating":5.39,"rmse":15.74},{"bias":-1.17,"califica":true,"color":"#56B4E9","confianza":"Alta","corr":0.43,"familia":"Convencionales","mae":4.23,"modelo":"AIFS025","n":30,"rating":5.37,"rmse":15.01},{"bias":-2.94,"califica":true,"color":"#F781BF","confianza":"Alta","corr":0.63,"familia":"ML","mae":3.67,"modelo":"HURDLE_XGB","n":30,"rating":5.36,"rmse":15.88},{"bias":0.94,"califica":true,"color":"#7570B3","confianza":"Alta","corr":0.62,"familia":"Postprocesamiento","mae":5.48,"modelo":"BC_CLASSIC_ICON","n":30,"rating":5.36,"rmse":13.35},{"bias":-0.64,"califica":true,"color":"#648FFF","confianza":"Alta","corr":0.53,"familia":"No convencionales","mae":5.22,"modelo":"UMGLOBAL10","n":30,"rating":5.34,"rmse":14.44},{"bias":-2.73,"califica":true,"color":"#785EF0","confianza":"Alta","corr":0.46,"familia":"ML","mae":3.57,"modelo":"ML_GBR","n":30,"rating":5.27,"rmse":15.83},{"bias":-2.85,"califica":true,"color":"#648FFF","confianza":"Alta","corr":0.51,"familia":"ML","mae":3.68,"modelo":"HURDLE_RF","n":30,"rating":5.25,"rmse":15.97},{"bias":-2.76,"califica":true,"color":"#FE6100","confianza":"Alta","corr":0.45,"familia":"ML","mae":3.71,"modelo":"ML_RF","n":30,"rating":5.2,"rmse":15.98},{"bias":-2.96,"califica":true,"color":"#FF7F00","confianza":"Alta","corr":0.39,"familia":"ML","mae":3.47,"modelo":"ML_ELASTICNET","n":30,"rating":5.2,"rmse":16.08},{"bias":-1.49,"califica":true,"color":"#4DAF4A","confianza":"Alta","corr":0.32,"familia":"Postprocesamiento","mae":4.02,"modelo":"QM_AIFS025","n":30,"rating":5.19,"rmse":16.27},{"bias":-3.04,"califica":true,"color":"#4DAF4A","confianza":"Alta","corr":0.42,"familia":"ML","mae":3.54,"modelo":"HURDLE_LOGIT_RIDGE","n":30,"rating":5.18,"rmse":16.17},{"bias":0.63,"califica":true,"color":"#A65628","confianza":"Alta","corr":0.47,"familia":"Postprocesamiento","mae":5.72,"modelo":"BC_CLASSIC_METEOBLUE","n":30,"rating":5.17,"rmse":14.63},{"bias":-3.0,"califica":true,"color":"#984EA3","confianza":"Alta","corr":0.35,"familia":"ML","mae":3.41,"modelo":"ML_HUBER","n":30,"rating":5.16,"rmse":16.15},{"bias":-3.02,"califica":true,"color":"#377EB8","confianza":"Alta","corr":0.39,"familia":"ML","mae":3.51,"modelo":"ML_RIDGE","n":30,"rating":5.16,"rmse":16.17},{"bias":-2.83,"califica":true,"color":"#B33DC6","confianza":"Alta","corr":0.37,"familia":"ML","mae":3.61,"modelo":"ML_ET","n":30,"rating":5.15,"rmse":16.1},{"bias":-2.88,"califica":true,"color":"#00A9A5","confianza":"Alta","corr":0.39,"familia":"No convencionales","mae":3.73,"modelo":"NEMSGLOBAL","n":30,"rating":5.12,"rmse":16.11},{"bias":-1.48,"califica":true,"color":"#4DAF4A","confianza":"Alta","corr":0.25,"familia":"No convencionales","mae":4.28,"modelo":"NEMSGLOBAL_E","n":30,"rating":5.05,"rmse":16.62},{"bias":0.85,"califica":true,"color":"#B33DC6","confianza":"Alta","corr":0.33,"familia":"Postprocesamiento","mae":6.19,"modelo":"BC_CLASSIC_AIFS025","n":30,"rating":4.83,"rmse":15.69},{"bias":-2.37,"califica":true,"color":"#B33DC6","confianza":"Alta","corr":0.19,"familia":"No convencionales","mae":4.68,"modelo":"SA01","n":30,"rating":4.72,"rmse":16.36},{"bias":-2.41,"califica":true,"color":"#A6761D","confianza":"Alta","corr":0.06,"familia":"No convencionales","mae":4.67,"modelo":"NEMSSA","n":30,"rating":4.57,"rmse":16.92}],"modo":"quantification","nombre":"Gye(Facult)","region":"Litoral","resumen":{"calif_media":5.6,"fechas_max":30,"mejor":"ENS_MEDIAN","mejor_confianza":"Alta","mejor_rating":9.48,"n_califican":45,"n_modelos":45},"ventana":"30"}
